Workbook
Name g0: Constants!$B$4

Sheet Mission success
A1: Spacecraft | B1: TVC engines, N | C1: TVC failure rate, each | D1: RCS thrusters, N | E1: RCS failure rate, each | F1: Max RCS failures tolerated | G1: Max TVC failures tolerated | H1: TVC ensemble success | I1: RCS ensemble success | J1: Mission success
A2: Ariane 5 ECA | B2: 1 | C2: 0.01 | G2: 0 | H2: 0.99 | J2: 0.99
A3: Delta IV Heavy | B3: 3 | C3: 0.01 | G3: 0 | H3: 0.970299 | J3: 0.970299
A4: Vega | B4: 1 | C4: 0.015 | G4: 0 | H4: 0.985 | J4: 0.985
A5: Vega-C | B5: 1 | C5: 0.015 | G5: 0 | H5: 0.985 | J5: 0.985
A6: Apollo Command & Service Module | B6: 1 | C6: 0.01 | D6: 16 | E6: 0.01 | F6: 1 | G6: 0 | H6: 0.99 | I6: 0.99959977 | J6: 0.99
A7: Apollo Lunar Module | B7: 1 | C7: 0.01 | D7: 16 | E7: 0.01 | F7: 1 | G7: 0 | H7: 0.99 | I7: 0.99959977 | J7: 0.99
A8: Crew Dragon (Dragon 2) | D8: 16 | E8: 0.01 | F8: 1 | I8: 0.99842073 | J8: 0.99842073
A9: Orion (CM + European Service Module) | B9: 1 | C9: 0.01 | D9: 24 | E9: 0.01 | F9: 3 | G9: 0 | H9: 0.99 | I9: 0.99999632 | J9: 0.99
A10: Cassini (Cassini-Huygens) | B10: 2 | C10: 0.01 | D10: 16 | E10: 0.005 | F10: 3 | G10: 1 | H10: 0.9999 | I10: 0.99999998 | J10: 0.9999
A11: Europa Clipper | D11: 24 | E11: 0.01 | F11: 3 | I11: 0.99990946 | J11: 0.99990946
A12: Juno | B12: 1 | C12: 0.01 | D12: 12 | E12: 0.005 | F12: 2 | G12: 0 | H12: 0.99 | I12: 0.99997341 | J12: 0.99
A13: New Horizons | B13: 4 | C13: 0.005 | D13: 12 | E13: 0.005 | F13: 1 | G13: 3 | H13: 1 | I13: 0.99985001 | J13: 0.99985001
A14: Voyager 1 | B14: 4 | C14: 0.005 | D14: 16 | E14: 0.005 | F14: 3 | G14: 3 | H14: 1 | I14: 0.99999998 | J14: 0.99999998
A15: GOES-16 (GOES-R)
A16: GOES-19 (GOES-U)
A17: Meteosat Second Generation (MSG) | B17: 2 | C17: 0.01 | D17: 6 | E17: 0.01 | F17: 0 | G17: 1 | H17: 0.9999 | I17: 0.97990399 | J17: 0.97990399
A18: Solar Dynamics Observatory (SDO) | B18: 1 | C18: 0.01 | D18: 8 | E18: 0.01 | F18: 1 | G18: 0 | H18: 0.99 | I18: 0.99930706 | J18: 0.99
A19: GRACE-FO (per satellite) | B19: 2 | C19: 0.003 | D19: 12 | E19: 0.003 | F19: 1 | G19: 1 | H19: 0.999991 | I19: 0.999946 | J19: 0.999946
A20: SMAP | D20: 8 | E20: 0.005 | F20: 1 | I20: 0.99982588 | J20: 0.99982588
A21: Sentinel-1A
A22: Sentinel-3A | D22: 8 | E22: 0.005 | F22: 1 | I22: 0.99982588 | J22: 0.99982588

Sheet Summary (check view)
A1: SUMMARY / CHECK VIEW
A2: Every cell below is a live formula pointing at the Data sheet - nothing is retyped, so this view cannot disagree with the source. Data sheet row = the row number here + 1.
A4: Category | B4: Spacecraft | C4: THRUST-TO-WEIGHT RATIO [-] | D4: Propellant mass fraction [-] | E4: Attitude units N | F4: Control DOF m | G4: Redundancy BEST (max failures) | H4: Redundancy WORST (guaranteed) | I4: Engine-out @ T/W>=1.0 (boosters) | J4: Engine-out @ T/W>=1.2 (boosters) | K4: Propulsive units | L4: PROPULSIVE redundancy (units-1)
A5: =Data!A2 | B5: =Data!B2 | C5: =Data!Z2 | D5: =Data!AA2 | E5: =Data!AK2 | F5: =Data!AM2 | G5: =Data!AO2 | H5: =Data!AP2 | I5: =IF(LEFT(Data!AQ2,3)="n/a","n/a",Data!AQ2) | J5: =IF(LEFT(Data!AR2,3)="n/a","n/a",Data!AR2) | K5: =Data!AS2 | L5: =Data!AU2
A6: =Data!A3 | B6: =Data!B3 | C6: =Data!Z3 | D6: =Data!AA3 | E6: =Data!AK3 | F6: =Data!AM3 | G6: =Data!AO3 | H6: =Data!AP3 | I6: =IF(LEFT(Data!AQ3,3)="n/a","n/a",Data!AQ3) | J6: =IF(LEFT(Data!AR3,3)="n/a","n/a",Data!AR3) | K6: =Data!AS3 | L6: =Data!AU3
A7: =Data!A4 | B7: =Data!B4 | C7: =Data!Z4 | D7: =Data!AA4 | E7: =Data!AK4 | F7: =Data!AM4 | G7: =Data!AO4 | H7: =Data!AP4 | I7: =IF(LEFT(Data!AQ4,3)="n/a","n/a",Data!AQ4) | J7: =IF(LEFT(Data!AR4,3)="n/a","n/a",Data!AR4) | K7: =Data!AS4 | L7: =Data!AU4
A8: =Data!A5 | B8: =Data!B5 | C8: =Data!Z5 | D8: =Data!AA5 | E8: =Data!AK5 | F8: =Data!AM5 | G8: =Data!AO5 | H8: =Data!AP5 | I8: =IF(LEFT(Data!AQ5,3)="n/a","n/a",Data!AQ5) | J8: =IF(LEFT(Data!AR5,3)="n/a","n/a",Data!AR5) | K8: =Data!AS5 | L8: =Data!AU5
A9: =Data!A6 | B9: =Data!B6 | C9: =Data!Z6 | D9: =Data!AA6 | E9: =Data!AK6 | F9: =Data!AM6 | G9: =Data!AO6 | H9: =Data!AP6 | I9: =IF(LEFT(Data!AQ6,3)="n/a","n/a",Data!AQ6) | J9: =IF(LEFT(Data!AR6,3)="n/a","n/a",Data!AR6) | K9: =Data!AS6 | L9: =Data!AU6
A10: =Data!A7 | B10: =Data!B7 | C10: =Data!Z7 | D10: =Data!AA7 | E10: =Data!AK7 | F10: =Data!AM7 | G10: =Data!AO7 | H10: =Data!AP7 | I10: =IF(LEFT(Data!AQ7,3)="n/a","n/a",Data!AQ7) | J10: =IF(LEFT(Data!AR7,3)="n/a","n/a",Data!AR7) | K10: =Data!AS7 | L10: =Data!AU7
A11: =Data!A8 | B11: =Data!B8 | C11: =Data!Z8 | D11: =Data!AA8 | E11: =Data!AK8 | F11: =Data!AM8 | G11: =Data!AO8 | H11: =Data!AP8 | I11: =IF(LEFT(Data!AQ8,3)="n/a","n/a",Data!AQ8) | J11: =IF(LEFT(Data!AR8,3)="n/a","n/a",Data!AR8) | K11: =Data!AS8 | L11: =Data!AU8
A12: =Data!A9 | B12: =Data!B9 | C12: =Data!Z9 | D12: =Data!AA9 | E12: =Data!AK9 | F12: =Data!AM9 | G12: =Data!AO9 | H12: =Data!AP9 | I12: =IF(LEFT(Data!AQ9,3)="n/a","n/a",Data!AQ9) | J12: =IF(LEFT(Data!AR9,3)="n/a","n/a",Data!AR9) | K12: =Data!AS9 | L12: =Data!AU9
A13: =Data!A10 | B13: =Data!B10 | C13: =Data!Z10 | D13: =Data!AA10 | E13: =Data!AK10 | F13: =Data!AM10 | G13: =Data!AO10 | H13: =Data!AP10 | I13: =IF(LEFT(Data!AQ10,3)="n/a","n/a",Data!AQ10) | J13: =IF(LEFT(Data!AR10,3)="n/a","n/a",Data!AR10) | K13: =Data!AS10 | L13: =Data!AU10
A14: =Data!A11 | B14: =Data!B11 | C14: =Data!Z11 | D14: =Data!AA11 | E14: =Data!AK11 | F14: =Data!AM11 | G14: =Data!AO11 | H14: =Data!AP11 | I14: =IF(LEFT(Data!AQ11,3)="n/a","n/a",Data!AQ11) | J14: =IF(LEFT(Data!AR11,3)="n/a","n/a",Data!AR11) | K14: =Data!AS11 | L14: =Data!AU11
A15: =Data!A12 | B15: =Data!B12 | C15: =Data!Z12 | D15: =Data!AA12 | E15: =Data!AK12 | F15: =Data!AM12 | G15: =Data!AO12 | H15: =Data!AP12 | I15: =IF(LEFT(Data!AQ12,3)="n/a","n/a",Data!AQ12) | J15: =IF(LEFT(Data!AR12,3)="n/a","n/a",Data!AR12) | K15: =Data!AS12 | L15: =Data!AU12
A16: =Data!A13 | B16: =Data!B13 | C16: =Data!Z13 | D16: =Data!AA13 | E16: =Data!AK13 | F16: =Data!AM13 | G16: =Data!AO13 | H16: =Data!AP13 | I16: =IF(LEFT(Data!AQ13,3)="n/a","n/a",Data!AQ13) | J16: =IF(LEFT(Data!AR13,3)="n/a","n/a",Data!AR13) | K16: =Data!AS13 | L16: =Data!AU13
... A25: =Data!A22 | B25: =Data!B22 | C25: =Data!Z22 | D25: =Data!AA22 | E25: =Data!AK22 | F25: =Data!AM22 | G25: =Data!AO22 | H25: =Data!AP22 | I25: =IF(LEFT(Data!AQ22,3)="n/a","n/a",Data!AQ22) | J25: =IF(LEFT(Data!AR22,3)="n/a","n/a",Data!AR22) | K25: =Data!AS22 | L25: =Data!AU22
A28: READING THE NUMBERS
A29: T/W and PMF Blank/n/d means the operator publishes no official value. 5 of 25 rows cannot form a T/W.
A30: Control DOF m 3 = 3-axis attitude. 6 = crewed vehicles (rendezvous/docking needs translation too). 2 = spin-stabilised. 1 = single-axis (electric propulsion).
A31: Redundancy BEST = N - (m+1). Theoretical ceiling, assumes survivors still positively span the control space.
A32: Redundancy WORST = floor(N/k) - 1. Guaranteed regardless of where the failures land.
A33: Engine-out Boosters only, from the liftoff T/W>=1 condition with payload included. Thrust criterion only - says nothing about remaining steering authority.
A34: PROPULSIVE redund. Non-boosters: mission fails only if no main-thrust engine works, so = units - 1.
A36: All redundancy figures are DERIVED, not cited - no manufacturer publishes fault-tolerance levels. See the Method & Definitions sheet for the derivation and the Data sheet for the per-row justification.

Sheet Constants
A1: Physical constants used by the formulas on the Data sheet
A3: Symbol | B3: Value | C3: Description
A4: g0 | B4: 9.80665 | C4: Standard gravity [m/s^2] (ISO 80000-3). Used for weight and for Isp -> exhaust velocity.

Sheet Method & Definitions
A1: SPACECRAFT PROPULSION & MASS DATABASE
A3: Purpose | B3: Total thrust (main/TVC + RCS + auxiliary), reference mass, thrust-to-weight ratio and propellant mass fraction for 25 vehicles in 5 classes, with every intermediate quantity computed by a live formula rather than hard-coded.
A4: Sourcing rule | B4: Primary/official sources only: the operator, manufacturer or agency responsible for the vehicle (NASA, ESA, NOAA, EUMETSAT, JPL, JHU-APL, SpaceX, ULA). No blogs, no encyclopedias, no enthusiast sites. Where an official source does not publish a value the cell reads 'n/d' and is NEVER filled with a third-party estimate, even a widely-repeated one.
A6: CALCULATION RULES APPLIED
A7: Boosters exclude payload | B7: Column U holds any payload mass contained in the published figure; column V = T - U is the launch-vehicle-only mass that the T/W uses. No remaining row needs it - the four booster masses are all published as vehicle-only - but the column stays so any launcher added later whose quoted mass includes a payload can be corrected in place.
A8: Boosters neglect RCS | B8: For Category = 'Boosters' the T/W thrust is main engines + strap-on boosters ONLY. Launch vehicle attitude control is by engine gimbal, and any cold-gas thrust is negligible against MN-class engines. The formula in column R switches on the category automatically.
A9: RCS-only vehicles | B9: Where a spacecraft has no main engine (Sentinel-3A, Voyager 1), the T/W is computed from the RCS tier alone. No special case is needed - the sum simply has one non-zero term.
A10: Main-engine-only vehicles | B10: Likewise, where the RCS is undisclosed but the main engine is known (Juno), T/W is computed from the main engine alone and the row is flagged PARTIAL.
A12: COLUMN DEFINITIONS
A13: Main / TVC engine | B13: Primary thrust-producing engine(s). 'TVC' is noted where the engine gimbals for thrust vector control. For launch vehicles this is the core-stage engine set.
A14: Aux / strap-on | B14: A third tier that is neither main engine nor attitude-control RCS: solid strap-on boosters for launch vehicles, the 8 R-4D-11 auxiliary engines for Orion, the APS for the Lunar Module.
A15: TOTAL main-engine thrust [N] | B15: =(thrust each) x (count). Excel: F*G
A16: TOTAL RCS thrust [N] | B16: =(thrust each) x (count). Excel: J*K
A17: TOTAL aux thrust [N] | B17: =(thrust each) x (count). Excel: N*O
A18: TOTAL installed thrust [N] | B18: =main + RCS + aux. Reads 'incomplete' if ANY tier is undisclosed, so a partial row can never masquerade as a complete one.
A19: THRUST USED FOR T/W [N] | B19: Sum of the disclosed tiers, with the booster rule above applied. For a PARTIAL row this is a LOWER BOUND, not the true total.
A20: VEHICLE MASS used for T/W | B20: =published mass - excluded payload.
A21: Vehicle weight [N] | B21: =vehicle mass x g0, g0 = 9.80665 read from the Constants sheet. Change it there and the whole sheet recalculates. Using Earth surface gravity does NOT imply the vehicle operates at 1 g.
A22: THRUST-TO-WEIGHT RATIO | B22: =thrust used for T/W / vehicle weight. Dimensionless. Shown in scientific notation because the sheet spans ~3e-5 (GRACE-FO cold gas) to ~2 (Ariane 5).
A23: Propellant mass fraction | B23: =propellant / vehicle mass. Nice-to-have; blank where the operator publishes no propellant load.
A24: Ideal delta-v [m/s] | B24: =Isp x g0 x ln(m_wet/m_dry) (Tsiolkovsky). Only computed where an official Isp exists.
A26: ACTUATOR-LEVEL REDUNDANCY MODEL
A27: Scope | B27: UNIT-level redundancy only: how many individual thrusters/engines can fail before control authority is lost. System-level redundancy (A/B strings, dual avionics, cold spares) is deliberately EXCLUDED. Where a system-level structure exists and materially changes the answer (Cassini's two branches, Cassini's two redundant RCS branches), it is called out in the justification cell.
A28: No official numbers exist | B28: Manufacturers do not publish fault-tolerance levels. Every value in this block is DERIVED, not cited. The inputs N (unit count), k (group count) and m (control DOF) are sourced where possible; the bounds are computed from them.
A30: Governing principle | B30: Rocket thrusters are ONE-SIDED actuators - they can push but not pull. A set of one-sided actuators can produce arbitrary control in an m-dimensional space only if their control vectors POSITIVELY SPAN that space. The minimum size of a positive spanning set of R^m is m+1, not m. This single fact drives the whole model.
A31: Min units for full authority | B31: =m + 1. For 3-axis attitude control (m=3) the floor is 4 thrusters, not 3. For a spin-stabilised spacecraft the third axis is held gyroscopically, so m=2 and the floor drops to 3 - which is why Juno and MSG score better than their small thruster counts suggest.
A32: m = 6 for crewed vehicles | B32: All five crewed vehicles are set to m=6, not m=3, because mission success requires full 6-DOF control: rendezvous and docking need independent TRANSLATION in x, y, z as well as rotation about all three axes. The minimum positive-spanning set rises from 4 to 7, which lowers every crewed best-case figure by 3 (e.g. Orion 20 -> 17, Apollo CSM 12 -> 9). Worst case is unaffected, since it is set by cluster geometry rather than by the dimension of the control space.
A33: Fine-control thrusters excluded | B33: Vernier / fine-pointing thrusters are NOT counted in the attitude tier, because losing them degrades pointing precision rather than causing mission failure. This removes the Shuttle's 6 x 25 lbf verniers (38 primary jets are counted, not 44) and keeps Voyager's 12 attitude thrusters out of its propulsive count. Where a spacecraft has only one class of thruster, nothing is excluded.
A34: BEST CASE (upper bound) | B34: =N - (m+1). Assumes the surviving units happen to be the ones that still positively span the control space, and that the control law can reconfigure to use them. This is the theoretical ceiling: no arrangement can do better.
A35: WORST CASE (lower bound) | B35: =floor(N/k) - 1. Reasoning: in a clustered layout the thrusters within one group share a mounting location and largely share torque directions, so the scarcest control direction is served by roughly N/k units. Failures that concentrate there remove that direction once all of them are gone; you are therefore GUARANTEED to survive one fewer than that. This is a bound you can rely on regardless of where the failures land.
A36: Why the two differ so much | B36: The spread between best and worst is a measure of how much the design depends on favourable failure locations. A tight spread (GRACE-FO 8 vs 1) means the layout is geometrically brittle; a wide one with a high floor (Shuttle 34 vs 11) means genuine designed-in margin.
A37: Validation of the generic rule | B37: For Orion the published functional split (2 of 6 clusters provide roll, so roll is the binding constraint at ~4 thrusters per direction) independently gives a worst case of 3 - identical to the generic N/k-1 result. That agreement is the main evidence that the generic rule is not arbitrary.
A39: ENGINE-OUT REDUNDANCY (boosters only)
A40: Criterion | B40: A launch vehicle must have T/W > 1 AT LIFTOFF WITH PAYLOAD. So the number of main engines that can be lost is the largest k satisfying (T_total - k x T_engine) >= m_liftoff x g0. Rearranged and floored, that is the formula in the sheet. Note this uses the WITH-payload mass (column T), unlike the T/W column which excludes payload - because engine-out is a real flight condition, not a normalised comparison.
A41: Two thresholds are given | B41: T/W >= 1.0 is the absolute floor (the vehicle merely leaves the pad). T/W >= 1.2 is the conservative figure, and is the one to quote. The 20% margin covers gravity losses, the reduced axial acceleration during the max-Q throttle bucket, and the steering losses incurred when a gimbal must trim the yaw/roll asymmetry an engine-out creates.
A42: Why max-Q is the binding case | B42: Liftoff T/W is the easiest condition to satisfy because propellant is still aboard and dynamic pressure is zero. Through max-Q the vehicle is deliberately throttled, so thrust margin is at its minimum exactly when aerodynamic and control loads are at their peak; an engine-out there costs both thrust AND gimbal authority, since the surviving engines must trim a large yawing moment. Any engine-out count derived from liftoff T/W alone is therefore OPTIMISTIC for the max-Q window, which is why the 1.2 column exists.
A43: Necessary, not sufficient | B43: The engine-out columns are a THRUST criterion only. They say nothing about whether the surviving engines can still steer. A vehicle whose strap-on boosters dominate the thrust budget can score well here while being uncontrollable after an engine-out, because the surviving gimbals cannot trim the asymmetry. Always read the justification cell alongside the number.
A45: PROPULSIVE ENGINE-OUT REDUNDANCY (non-boosters)
A46: Criterion | B46: For spacecraft rather than launch vehicles the test is mission completion, not liftoff: the mission fails only if NO main-thrust engine works. Redundancy is therefore simply (propulsive units - 1). One surviving engine is enough - the burn just takes longer.
A47: EACH UNIT COUNTS ONCE | B47: A physical thruster belongs to the attitude tier OR the propulsive tier, never both. Where one homogeneous set does both jobs (Europa Clipper's 24 engines, Crew Dragon's 16 Dracos) it is counted ONCE, in the attitude tier, and the propulsive term contributes nothing - the vehicle has no separable engine. Voyager 1 and New Horizons are the subtle version - their 16 thrusters split into 12 attitude plus 4 trajectory-correction units, so only the 12 populate the attitude tier.
A48: Propulsive tier = MAIN tier | B48: The propulsive count is the MAIN-engine tier only, never main + aux. Orion briefly counted 9 (OMS-E + 8 auxiliary engines) and was the only row in the sheet doing so; the auxiliary engines already appear as their own thrust tier, so counting them again inflated the score. Apollo LM sets the precedent - it has an APS aux tier and still counts 1.
A49: Which units count | B49: Only units that can deliver the primary TRANSLATIONAL thrust the mission needs. Attitude and fine-pointing thrusters are excluded unless they are genuinely the propulsive tier (New Horizons, Voyager). Orion counts the OMS-E alone, NOT the 8 auxiliary engines - those are their own tier. Crew Dragon and Europa Clipper have no separable engine tier at all, since their thrusters are already counted as the attitude tier.
A50: What it reveals | B50: Almost every crewed and deep-space vehicle here has a SINGLE main engine. Orion, Apollo CSM, Apollo LM, Juno and SDO all score 0: single-engine single-point failures. The Apollo LM is the extreme case, with no backup and no abort mode for the ascent engine; Grumman bought reliability through radical simplicity (pressure-fed, ablatively cooled, no throttle, no gimbal) instead of through redundancy. That trade - simplicity versus redundancy - is worth a paragraph in any thesis using this sheet.
A51: Count vs effective redundancy | B51: A high count is not automatically high redundancy. Europa Clipper has 24 units but is thrust-limited (only 8 of 24 fire at once). Read the propulsive justification column before quoting these.
A53: Solid motors score zero by construction | B53: A solid booster cannot be throttled, shut down or lost gracefully - its failure is a loss of vehicle, not a degraded mode. Vega, Vega-C and the Ariane 5 EAPs therefore have no actuator redundancy at all during boost, which is a real architectural difference from a liquid engine cluster. IMPORTANT DISTINCTION: this is NOT because they lack thrust vector control. All of them steer by gimballed/movable nozzle - ESA documents electromechanical TVC actuators on both the P80 and the P120C. TVC gives steering authority; redundancy is about surviving the loss of a unit, and a single solid motor cannot survive its own failure however well it steers.
A55: COLOUR CODING
A56: Green | B56: Headline results: thrust totals, T/W, PMF.
A57: Yellow | B57: Computed by formula from the white input columns. Do not overwrite.
A58: White | B58: Directly-cited input data. Every number traces to a source column.
A60: ROWS WHERE T/W STILL CANNOT BE COMPUTED (5 of 25)
A61: SMAP | B61: Thrust fully published (8 x 4.5 N), launch mass NOT published by NASA/JPL. Add an official mass and the row completes itself.
A62: Sentinel-1A | B62: Mass and propellant published, thruster count and thrust NOT published by ESA.
A63: GOES-16 / GOES-19 | B63: Fuelled and dry mass published by NOAA, propulsion thrust NOT published. No substitute exists - see below.
A64: Crew Dragon | B64: Thrust published by NASA, gross mass NOT published by SpaceX.
A66: KNOWN LIMITATIONS - READ BEFORE CITING
A67: Operational GEO is a data desert | B67: Commercial and operational GEO satellite operators essentially never publish thruster ratings. SDO (a NASA science mission in inclined GEO), MSG (ESA published BR-153) were the only GEO-class vehicles found with usable thrust data. This is a genuine finding about data availability.
A68: Vehicles dropped for lack of mass | B68: Falcon 9 and Atlas V 551 were removed because neither SpaceX nor ULA publishes a gross liftoff mass in any official document, so no T/W could be formed. They were replaced by Vega-C and Vega, where ESA publishes both thrust and liftoff mass. Hubble was replaced by GRACE-FO because HST has no propulsion at all.
A69: Mixed thrust ratings | B69: Several rows mix sea-level and vacuum ratings, or quote peak rather than ignition thrust, because that is how the operator publishes them (Ariane 5, Vega-C). Every such case is flagged in the Notes column and the affected T/W is an upper bound.
A70: Non-simultaneous thrust | B70: Apollo LM (DPS vs APS), Cassini (redundant engine and RCS branch), Europa Clipper (8 of 24 engines) and Crew Dragon (abort vs orbital) all have installed thrust well above what can fire at once. Read the Notes before using those totals.

Sheet Data
A1: Category | B1: Spacecraft | C1: Operator / Prime contractor | D1: Reference configuration | E1: Main / TVC engine designation | F1: Main engine thrust, each [N] | G1: No. of main engines | H1: TOTAL main-engine thrust [N] | I1: RCS thruster designation | J1: RCS thrust, each [N] | K1: No. of RCS thrusters | L1: TOTAL RCS thrust [N] | M1: Aux / strap-on designation | N1: Aux thrust, each [N] | O1: No. of aux units | P1: TOTAL aux thrust [N] | Q1: TOTAL installed thrust, all tiers [N] | R1: THRUST USED FOR T/W [N] | S1: Thrust data complete? | T1: Reference mass, as published [kg] | U1: Payload mass excluded [kg] | V1: VEHICLE MASS used for T/W [kg] | W1: Dry mass [kg] | X1: Propellant mass [kg] | Y1: Vehicle weight at Earth surface [N] | Z1: THRUST-TO-WEIGHT RATIO [-] | AA1: Propellant mass fraction [-] | AB1: Mass ratio m_wet/m_dry [-] | AC1: Isp [s] | AD1: Ideal delta-v [m/s] | AE1: Verification status | AF1: Notes, caveats and discrepancies | AG1: Source - main engine thrust | AH1: Source - RCS thrust | AI1: Source - mass | AJ1: REDUNDANCY: actuator tier assessed | AK1: Units installed, N | AL1: Actuator groups/clusters, k | AM1: Control DOF required, m | AN1: Min units for full authority (m+1) | AO1: BEST CASE: max unit failures tolerated | AP1: WORST CASE: unit failures guaranteed tolerated | AQ1: Engine-out: max engines losable at T/W>=1.0 (liftoff, incl. payload) | AR1: Engine-out: max engines losable at T/W>=1.2 (max-Q conservative) | AS1: Propulsive units counted (main-thrust capable) | AT1: Which units are counted as propulsive | AU1: PROPULSIVE ENGINE-OUT REDUNDANCY (units - 1) | AV1: Redundancy basis & justification | AW1: Propulsive redundancy justification
A2: Boosters | B2: Delta IV Heavy | C2: United Launch Alliance | D2: Liftoff (3 Common Booster Cores) | E2: RS-68A (gimballed) | F2: 3123000 | G2: 3 | H2: =IFERROR(F2*G2,"n/d") | I2: None at vehicle level | J2: 0 | K2: 0 | L2: =IFERROR(J2*K2,"n/d") | M2: None | N2: 0 | O2: 0 | P2: =IFERROR(N2*O2,"n/d") | Q2: =IFERROR(H2+L2+P2,"incomplete") | R2: =IF(A2="Boosters",SUM(H2,P2),SUM(H2,L2,P2)) | S2: =IF(A2="Boosters",IF(AND(ISNUMBER(H2),ISNUMBER(P2)),"complete","PARTIAL"),IF(ISNUMBER(Q2),"complete","PARTIAL")) | T2: 725700 | U2: 0 | V2: =IFERROR(T2-U2,"n/d") | W2: n/d | X2: =IFERROR(V2-W2,"n/d") | Y2: =IFERROR(V2*g0,"n/d") | Z2: =IF(AND(S2="PARTIAL",R2=0),"n/d",IFERROR(R2/Y2,"n/d")) | AA2: =IFERROR(X2/V2,"n/d") | AB2: =IFERROR(V2/W2,IFERROR(V2/(V2-X2),"n/d")) | AC2: n/d | AD2: =IFERROR(AC2*g0*LN(AB2),"n/d") | AE2: Direct - official page read | AF2: ULA describes 725,700 kg as the mass of 'the fully fueled rocket', i.e. vehicle only, so no payload is subtracted. CAUTION: ULA's own text writes '702,000 pounds (312.3 kiloNewtons)' - that conversion is wrong by a factor of 10. 702,000 lbf = 3,123 kN, and ULA's own stated combined 9.4 MN confirms 3 x 3,123 kN. Cite the pound-force value, never ULA's kN value. | AG2: ULA, 'NROL-70: Final Delta IV Heavy prepared for launch': https://blog.ulalaunch.com/blog/nrol-70-final-delta-iv-heavy-prepared-for-launch | AH2: n/a at vehicle level | AI2: ULA NROL-70 article: 'gross liftoff mass of 1.6 million pounds (725,700 kg)' | AJ2: n/a - no RCS tier at vehicle level | AK2: n/a | AL2: n/a | AM2: n/a | AN2: =IFERROR(AM2+1,"n/a") | AO2: =IFERROR(MAX(0,AK2-AN2),"n/a") | AP2: =IFERROR(MAX(0,FLOOR(AK2/AL2,1)-1),"n/a") | AQ2: =IF(A2="Boosters",IFERROR(MAX(0,MIN(G2-1,FLOOR((R2-T2*g0)/F2,1))),"n/a"),"n/a - not a liftoff vehicle") | AR2: =IF(A2="Boosters",IFERROR(MAX(0,MIN(G2-1,FLOOR((R2-1.2*T2*g0)/F2,1))),"n/a"),"n/a - not a liftoff vehicle") | AS2: n/a | AU2: =IFERROR(MAX(0,AS2-1),"n/a") | AV2: Steering by RS-68A gimbal only. Engine-out at liftoff = 0: with T/W = 1.32 on 3 engines, losing one drops thrust to 6,246 kN against a weight of 7,118 kN, i.e. T/W = 0.88 and the vehicle cannot fly. This is the classic low-engine-count penalty - a 3-engine cluster has no liftoff engine-out capability unless T/W > 1.5.
A3: Boosters | B3: Ariane 5 ECA | C3: ESA / Arianespace | D3: Liftoff (EPC + 2 EAP) | E3: Vulcain 2 (gimballed, sea level) | F3: 960000 | G3: 1 | H3: =IFERROR(F3*G3,"n/d") | I3: None at vehicle level | J3: 0 | K3: 0 | L3: =IFERROR(J3*K3,"n/d") | M3: EAP P241 solid booster | N3: 7080000 | O3: 2 | P3: =IFERROR(N3*O3,"n/d") | Q3: =IFERROR(H3+L3+P3,"incomplete") | R3: =IF(A3="Boosters",SUM(H3,P3),SUM(H3,L3,P3)) | S3: =IF(A3="Boosters",IF(AND(ISNUMBER(H3),ISNUMBER(P3)),"complete","PARTIAL"),IF(ISNUMBER(Q3),"complete","PARTIAL")) | T3: 780000 | U3: 0 | V3: =IFERROR(T3-U3,"n/d") | W3: n/d | X3: =IFERROR(V3-W3,"n/d") | Y3: =IFERROR(V3*g0,"n/d") | Z3: =IF(AND(S3="PARTIAL",R3=0),"n/d",IFERROR(R3/Y3,"n/d")) | AA3: =IFERROR(X3/V3,"n/d") | AB3: =IFERROR(V3/W3,IFERROR(V3/(V3-X3),"n/d")) | AC3: n/d | AD3: =IFERROR(AC3*g0*LN(AB3),"n/d") | AE3: Official page via search summary - re-verify | AF3: ESA does not state whether the 780 t liftoff mass includes a payload, so nothing is subtracted (a typical GTO payload would be ~10 t, i.e. ~1% - it would lower T/W by ~1%). The computed 15,120 kN matches ESA's stated liftoff total exactly. CAVEAT: 7,080 kN is the EAP PEAK thrust reached shortly after ignition, not thrust at pad release (~6,470 kN each), so the resulting T/W of 1.98 is high; true liftoff T/W is nearer 1.7. | AG3: ESA, Ariane 5 ECA: 2 boosters 7,080 kN each, core 960 kN, total 15,120 kN: https://www.esa.int/Enabling_Support/Space_Transportation/Ariane/Ariane_5_ECA | AH3: n/a at vehicle level | AI3: ESA, Ariane 5 ECA: liftoff mass 780 tonnes | AJ3: n/a - no RCS tier at vehicle level | AK3: n/a | AL3: n/a | AM3: n/a | AN3: =IFERROR(AM3+1,"n/a") | AO3: =IFERROR(MAX(0,AK3-AN3),"n/a") | AP3: =IFERROR(MAX(0,FLOOR(AK3/AL3,1)-1),"n/a") | AQ3: =IF(A3="Boosters",IFERROR(MAX(0,MIN(G3-1,FLOOR((R3-T3*g0)/F3,1))),"n/a"),"n/a - not a liftoff vehicle") | AR3: =IF(A3="Boosters",IFERROR(MAX(0,MIN(G3-1,FLOOR((R3-1.2*T3*g0)/F3,1))),"n/a"),"n/a - not a liftoff vehicle") | AS3: n/a | AU3: =IFERROR(MAX(0,AS3-1),"n/a") | AV3: Single Vulcain 2 core engine, so core engine-out redundancy is structurally 0. The two EAP solid boosters cannot be shut down, throttled or lost: a solid motor failure is not a degraded mode but a loss of vehicle. Solid-boosted launchers therefore have ZERO actuator redundancy during the boost phase by construction.
A4: Boosters | B4: Vega-C | C4: ESA / Avio / Arianespace | D4: Liftoff (P120C first stage) | E4: P120C solid motor (max thrust) | F4: 4650000 | G4: 1 | H4: =IFERROR(F4*G4,"n/d") | I4: None at vehicle level | J4: 0 | K4: 0 | L4: =IFERROR(J4*K4,"n/d") | M4: None (single-body vehicle, no strap-ons) | N4: 0 | O4: 0 | P4: =IFERROR(N4*O4,"n/d") | Q4: =IFERROR(H4+L4+P4,"incomplete") | R4: =IF(A4="Boosters",SUM(H4,P4),SUM(H4,L4,P4)) | S4: =IF(A4="Boosters",IF(AND(ISNUMBER(H4),ISNUMBER(P4)),"complete","PARTIAL"),IF(ISNUMBER(Q4),"complete","PARTIAL")) | T4: 210000 | U4: 0 | V4: =IFERROR(T4-U4,"n/d") | W4: n/d | X4: =IFERROR(V4-W4,"n/d") | Y4: =IFERROR(V4*g0,"n/d") | Z4: =IF(AND(S4="PARTIAL",R4=0),"n/d",IFERROR(R4/Y4,"n/d")) | AA4: =IFERROR(X4/V4,"n/d") | AB4: =IFERROR(V4/W4,IFERROR(V4/(V4-X4),"n/d")) | AC4: n/d | AD4: =IFERROR(AC4*g0*LN(AB4),"n/d") | AE4: Official page via search summary - re-verify | AF4: Single-body solid launcher, so liftoff thrust is the first stage alone. ESA does not state whether the 210 t liftoff mass includes payload; Vega-C's capacity is only ~2,200 kg (~1%) so the effect is negligible and nothing is subtracted. 4,650 kN is the MAXIMUM thrust of the P120C, so this T/W is an upper bound. | AG4: ESA, Vega-C: 'The P120C motor delivers a maximum thrust of 4650 kN': https://www.esa.int/Enabling_Support/Space_Transportation/Vega/Vega-C | AH4: n/a at vehicle level | AI4: ESA, Vega-C: 'a mass at liftoff of 210 tonnes' | AJ4: n/a - no RCS tier at vehicle level | AK4: n/a | AL4: n/a | AM4: n/a | AN4: =IFERROR(AM4+1,"n/a") | AO4: =IFERROR(MAX(0,AK4-AN4),"n/a") | AP4: =IFERROR(MAX(0,FLOOR(AK4/AL4,1)-1),"n/a") | AQ4: =IF(A4="Boosters",IFERROR(MAX(0,MIN(G4-1,FLOOR((R4-T4*g0)/F4,1))),"n/a"),"n/a - not a liftoff vehicle") | AR4: =IF(A4="Boosters",IFERROR(MAX(0,MIN(G4-1,FLOOR((R4-1.2*T4*g0)/F4,1))),"n/a"),"n/a - not a liftoff vehicle") | AS4: n/a | AU4: =IFERROR(MAX(0,AS4-1),"n/a") | AV4: HAS TVC - retained on that basis. ESA states the P120C nozzle 'is gimballed to control the flight of the launcher', steered by electro-mechanical actuators. Zero actuator redundancy nonetheless: there is one actuator (the motor) and one steering mechanism (its nozzle). Note the distinction - having TVC is not the same as having redundancy. Redundancy exists only in the avionics driving the TVC, which is system-level and out of scope here.
A5: Boosters | B5: Vega | C5: ESA / Avio / Arianespace | D5: Liftoff (P80 first stage) | E5: P80 solid motor | F5: 2942000 | G5: 1 | H5: =IFERROR(F5*G5,"n/d") | I5: None at vehicle level | J5: 0 | K5: 0 | L5: =IFERROR(J5*K5,"n/d") | M5: None (single-body vehicle, no strap-ons) | N5: 0 | O5: 0 | P5: =IFERROR(N5*O5,"n/d") | Q5: =IFERROR(H5+L5+P5,"incomplete") | R5: =IF(A5="Boosters",SUM(H5,P5),SUM(H5,L5,P5)) | S5: =IF(A5="Boosters",IF(AND(ISNUMBER(H5),ISNUMBER(P5)),"complete","PARTIAL"),IF(ISNUMBER(Q5),"complete","PARTIAL")) | T5: 137000 | U5: 0 | V5: =IFERROR(T5-U5,"n/d") | W5: n/d | X5: =IFERROR(V5-W5,"n/d") | Y5: =IFERROR(V5*g0,"n/d") | Z5: =IF(AND(S5="PARTIAL",R5=0),"n/d",IFERROR(R5/Y5,"n/d")) | AA5: =IFERROR(X5/V5,"n/d") | AB5: =IFERROR(V5/W5,IFERROR(V5/(V5-X5),"n/d")) | AC5: n/d | AD5: =IFERROR(AC5*g0*LN(AB5),"n/d") | AE5: Official page via search summary - re-verify | AF5: ESA quotes P80 thrust as '300 tonnes of thrust' (tonnes-force), converted here as 300,000 kgf x 9.80665 = 2,942 kN. Included alongside Vega-C as a direct predecessor comparison: same architecture, ~35% less liftoff mass and ~37% less thrust, giving an almost identical T/W - a clean illustration that T/W is roughly preserved when a solid launcher is scaled. | AG5: ESA, The Vega stages: 'At liftoff the P80 will provide Vega with 300 tonnes of thrust for 106.7 seconds': https://www.esa.int/Enabling_Support/Space_Transportation/Vega/The_Vega_stages | AH5: n/a at vehicle level | AI5: ESA, Vega: 'Vega weighed a total of 137 tonnes at liftoff': https://www.esa.int/Enabling_Support/Space_Transportation/Launch_vehicles/Vega | AJ5: n/a - no RCS tier at vehicle level | AK5: n/a | AL5: n/a | AM5: n/a | AN5: =IFERROR(AM5+1,"n/a") | AO5: =IFERROR(MAX(0,AK5-AN5),"n/a") | AP5: =IFERROR(MAX(0,FLOOR(AK5/AL5,1)-1),"n/a") | AQ5: =IF(A5="Boosters",IFERROR(MAX(0,MIN(G5-1,FLOOR((R5-T5*g0)/F5,1))),"n/a"),"n/a - not a liftoff vehicle") | AR5: =IF(A5="Boosters",IFERROR(MAX(0,MIN(G5-1,FLOOR((R5-1.2*T5*g0)/F5,1))),"n/a"),"n/a - not a liftoff vehicle") | AS5: n/a | AU5: =IFERROR(MAX(0,AS5-1),"n/a") | AV5: HAS TVC - retained on that basis. ESA describes the P80 as carrying 'a Thrust Vector Control (TVC) system consisting of two electromechanical actuators that operate a movable nozzle' to control pitch and yaw. Otherwise identical to Vega-C: included as the scaled-down comparison, and redundancy does not improve with scale in a single-motor solid architecture.
A6: LEO Satellites | B6: GRACE-FO (per satellite) | C6: NASA / JPL / GFZ | D6: Launch configuration | E6: 40 mN cold-gas orbit-control thruster (rear panel) | F6: 0.04 | G6: 2 | H6: =IFERROR(F6*G6,"n/d") | I6: 10 mN cold-gas attitude thruster (2 on each of 6 faces) | J6: 0.01 | K6: 12 | L6: =IFERROR(J6*K6,"n/d") | M6: None | N6: 0 | O6: 0 | P6: =IFERROR(N6*O6,"n/d") | Q6: =IFERROR(H6+L6+P6,"incomplete") | R6: =IF(A6="Boosters",SUM(H6,P6),SUM(H6,L6,P6)) | S6: =IF(A6="Boosters",IF(AND(ISNUMBER(H6),ISNUMBER(P6)),"complete","PARTIAL"),IF(ISNUMBER(Q6),"complete","PARTIAL")) | T6: 600.2 | U6: 0 | V6: =IFERROR(T6-U6,"n/d") | X6: 31.3 | Y6: =IFERROR(V6*g0,"n/d") | Z6: =IF(AND(S6="PARTIAL",R6=0),"n/d",IFERROR(R6/Y6,"n/d")) | AA6: =IFERROR(X6/V6,"n/d") | AB6: =IFERROR(V6/W6,IFERROR(V6/(V6-X6),"n/d")) | AC6: n/d | AD6: =IFERROR(AC6*g0*LN(AB6),"n/d") | AE6: Direct - official page read | AF6: Fully-closed low-thrust case: 2x40 mN + 12x10 mN = 0.2 N on a 600 kg satellite, T/W ~ 3.4e-5, the smallest in this sheet. Cold gas (GN2), no combustion. The 'main engine' tier is simply the two orbit-control thrusters - there is no chemical engine. Figures are per satellite, not for the twin pair. | AG6: NASA JPL GRACE-FO Launch Press Kit: 'two 40 millinewton orbit-control thrusters mounted on the rear-panel': https://www.jpl.nasa.gov/news/press_kits/grace-fo/mission/spacecraft/ | AH6: Same press kit: 'twelve 10 millinewton thrusters mounted two on each of the six sides of the satellite' | AI6: Same press kit: 'Each GRACE-FO satellite weighs 1,323.2 pounds (600.2 kilograms), including onboard propellant'; '69 pounds (31.3 kilograms) of gaseous nitrogen as propellant' | AJ6: Attitude tier: 12 x 10 mN cold-gas thrusters | AK6: 12 | AL6: 6 | AM6: 3 | AN6: =IFERROR(AM6+1,"n/a") | AO6: =IFERROR(MAX(0,AK6-AN6),"n/a") | AP6: =IFERROR(MAX(0,FLOOR(AK6/AL6,1)-1),"n/a") | AQ6: =IF(A6="Boosters",IFERROR(MAX(0,MIN(G6-1,FLOOR((R6-T6*g0)/F6,1))),"n/a"),"n/a - not a liftoff vehicle") | AR6: =IF(A6="Boosters",IFERROR(MAX(0,MIN(G6-1,FLOOR((R6-1.2*T6*g0)/F6,1))),"n/a"),"n/a - not a liftoff vehicle") | AS6: 2 | AT6: 2 x 40 mN cold-gas orbit-control thrusters | AU6: =IFERROR(MAX(0,AS6-1),"n/a") | AV6: k = 6 is PUBLISHED, not assumed: JPL states 'two on each of the six sides of the satellite'. That geometry is the worst case for graceful degradation - the two thrusters on a given face are the only source of torque in that face's direction, so losing both removes a control direction outright. Hence worst case = 1. Best case = 12 - 4 = 8 assumes surviving thrusters happen to positively span R^3. | AW6: Only the two rear-panel 40 mN units produce orbit-changing thrust; the 12 x 10 mN attitude thrusters cannot maintain the constellation. Redundancy 1.
A7: LEO Satellites | B7: Sentinel-3A | C7: ESA / EUMETSAT / Copernicus | D7: Launch configuration | E7: None (no main/apogee engine) | F7: 0 | G7: 0 | H7: =IFERROR(F7*G7,"n/d") | I7: 1 N hydrazine monopropellant thruster | J7: 1 | K7: 8 | L7: =IFERROR(J7*K7,"n/d") | M7: None | N7: 0 | O7: 0 | P7: =IFERROR(N7*O7,"n/d") | Q7: =IFERROR(H7+L7+P7,"incomplete") | R7: =IF(A7="Boosters",SUM(H7,P7),SUM(H7,L7,P7)) | S7: =IF(A7="Boosters",IF(AND(ISNUMBER(H7),ISNUMBER(P7)),"complete","PARTIAL"),IF(ISNUMBER(Q7),"complete","PARTIAL")) | T7: 1250 | U7: 0 | V7: =IFERROR(T7-U7,"n/d") | W7: n/d | X7: =IFERROR(V7-W7,"n/d") | Y7: =IFERROR(V7*g0,"n/d") | Z7: =IF(AND(S7="PARTIAL",R7=0),"n/d",IFERROR(R7/Y7,"n/d")) | AA7: =IFERROR(X7/V7,"n/d") | AB7: =IFERROR(V7/W7,IFERROR(V7/(V7-X7),"n/d")) | AC7: n/d | AD7: =IFERROR(AC7*g0*LN(AB7),"n/d") | AE7: Direct - primary doc read | AF7: One of the few Earth-observation satellites where ESA publishes both thruster count and thrust. All propulsion is the RCS tier, so per your rule the T/W is computed from the RCS alone: 8 N / 12.26 kN = 6.5e-4. Propellant load is not published, so PMF cannot be computed. | AG7: n/a - no main/apogee engine | AH7: ESA Sentinel-3 Data Sheet: '8x1N hydrazine thrusters for in-plane & out-out plane': https://esamultimedia.esa.int/docs/S3-Data_Sheet.pdf | AI7: ESA Sentinel-3 Data Sheet: 'Launch Mass: 1250 kg' | AJ7: Attitude tier: 8 x 1 N hydrazine thrusters | AK7: 8 | AL7: 4 | AM7: 3 | AN7: =IFERROR(AM7+1,"n/a") | AO7: =IFERROR(MAX(0,AK7-AN7),"n/a") | AP7: =IFERROR(MAX(0,FLOOR(AK7/AL7,1)-1),"n/a") | AQ7: =IF(A7="Boosters",IFERROR(MAX(0,MIN(G7-1,FLOOR((R7-T7*g0)/F7,1))),"n/a"),"n/a - not a liftoff vehicle") | AR7: =IF(A7="Boosters",IFERROR(MAX(0,MIN(G7-1,FLOOR((R7-1.2*T7*g0)/F7,1))),"n/a"),"n/a - not a liftoff vehicle") | AS7: n/a | AT7: no main-thrust tier | AU7: =IFERROR(MAX(0,AS7-1),"n/a") | AV7: ESA publishes the count (8) but not the layout; k = 4 is ASSUMED from the near-universal practice of mounting 1 N monopropellant thrusters in opposed pairs. If the true layout is 2 clusters of 4, worst case rises to 3. Flagged as an assumption - verify against an ESA layout drawing before citing the worst-case number. | AW7: All eight 1 N thrusters serve both orbit maintenance and attitude, so there is no separable propulsive tier.
A8: LEO Satellites | B8: SMAP | C8: NASA / JPL | D8: On-orbit | E8: None (no main engine) | F8: 0 | G8: 0 | H8: =IFERROR(F8*G8,"n/d") | I8: 4.5 N hydrazine monopropellant thruster (MONARC-5) | J8: 4.5 | K8: 8 | L8: =IFERROR(J8*K8,"n/d") | M8: None | N8: 0 | O8: 0 | P8: =IFERROR(N8*O8,"n/d") | Q8: =IFERROR(H8+L8+P8,"incomplete") | R8: =IF(A8="Boosters",SUM(H8,P8),SUM(H8,L8,P8)) | S8: =IF(A8="Boosters",IF(AND(ISNUMBER(H8),ISNUMBER(P8)),"complete","PARTIAL"),IF(ISNUMBER(Q8),"complete","PARTIAL")) | T8: n/d | U8: 0 | V8: =IFERROR(T8-U8,"n/d") | W8: n/d | X8: 80 | Y8: =IFERROR(V8*g0,"n/d") | Z8: =IF(AND(S8="PARTIAL",R8=0),"n/d",IFERROR(R8/Y8,"n/d")) | AA8: =IFERROR(X8/V8,"n/d") | AB8: =IFERROR(V8/W8,IFERROR(V8/(V8-X8),"n/d")) | AC8: n/d | AD8: =IFERROR(AC8*g0*LN(AB8),"n/d") | AE8: Direct - primary doc read (thrust); mass NOT obtained officially | AF8: T/W CANNOT BE CLOSED. Thrust is fully documented (8 x 4.5 N = 36 N) and usable hydrazine is 80 kg, but no official NASA/JPL source located in this research pass states the observatory launch mass. The widely repeated 944 kg figure does not appear in any JPL document I could reach, so it is deliberately NOT entered. Supply an official mass and the T/W and PMF cells will compute themselves. | AG8: n/a - no main engine | AH8: NASA JPL DESCANSO, SMAP mission summary: 'Eight 4.5-newton (N) thrusters are located on four brackets off the propulsion deck'; tank 'capacity for 80 kg of usable hydrazine': https://descanso.jpl.nasa.gov/NEDSummary/SMAP_201703--RefUpdates-A--03.pdf | AI8: NOT OBTAINED from an official source - do not fill from a non-official site | AJ8: Attitude tier: 8 x 4.5 N MONARC-5 thrusters | AK8: 8 | AL8: 4 | AM8: 3 | AN8: =IFERROR(AM8+1,"n/a") | AO8: =IFERROR(MAX(0,AK8-AN8),"n/a") | AP8: =IFERROR(MAX(0,FLOOR(AK8/AL8,1)-1),"n/a") | AQ8: =IF(A8="Boosters",IFERROR(MAX(0,MIN(G8-1,FLOOR((R8-T8*g0)/F8,1))),"n/a"),"n/a - not a liftoff vehicle") | AR8: =IF(A8="Boosters",IFERROR(MAX(0,MIN(G8-1,FLOOR((R8-1.2*T8*g0)/F8,1))),"n/a"),"n/a - not a liftoff vehicle") | AS8: n/a | AT8: no main-thrust tier | AU8: =IFERROR(MAX(0,AS8-1),"n/a") | AV8: k = 4 is PUBLISHED: JPL states the eight thrusters are 'located on four brackets off the propulsion deck', with four of the eight dedicated to yaw control. Worst case = 1 follows from the bracket pairing. Best case = 4. Note the published functional split (4 for yaw) means the true worst case may be lower than the geometric estimate if the yaw four are not interchangeable. | AW8: Four of the eight 4.5 N thrusters provide +Z orbit-correction thrust, but they are not a separable engine tier.
A9: LEO Satellites | B9: Sentinel-1A | C9: ESA / Copernicus | D9: Launch configuration | E9: None (no main/apogee engine) | F9: 0 | G9: 0 | H9: =IFERROR(F9*G9,"n/d") | I9: Catalytic hydrazine monopropellant thruster | J9: n/d | K9: n/d | L9: =IFERROR(J9*K9,"n/d") | M9: None | N9: 0 | O9: 0 | P9: =IFERROR(N9*O9,"n/d") | Q9: =IFERROR(H9+L9+P9,"incomplete") | R9: =IF(A9="Boosters",SUM(H9,P9),SUM(H9,L9,P9)) | S9: =IF(A9="Boosters",IF(AND(ISNUMBER(H9),ISNUMBER(P9)),"complete","PARTIAL"),IF(ISNUMBER(Q9),"complete","PARTIAL")) | T9: 2300 | U9: 0 | V9: =IFERROR(T9-U9,"n/d") | W9: n/d | X9: 130 | Y9: =IFERROR(V9*g0,"n/d") | Z9: =IF(AND(S9="PARTIAL",R9=0),"n/d",IFERROR(R9/Y9,"n/d")) | AA9: =IFERROR(X9/V9,"n/d") | AB9: =IFERROR(V9/W9,IFERROR(V9/(V9-X9),"n/d")) | AC9: n/d | AD9: =IFERROR(AC9*g0*LN(AB9),"n/d") | AE9: Direct - primary doc read (mass); thrust NOT published | AF9: T/W CANNOT BE CLOSED. ESA publishes launch mass 2,300 kg including 130 kg of monopropellant (so PMF = 5.65% computes fine) and confirms 'a dedicated propulsion system utilising hydrazine propellant and catalytic reaction thrusters', but publishes neither thruster count nor thrust anywhere in ESA SP-1322/1. Retained rather than substituted because it documents the PMF side of the problem. | AG9: NOT PUBLISHED by ESA | AH9: ESA SP-1322/1: propulsion is 'hydrazine propellant and catalytic reaction thrusters' - no count or thrust given: https://earth.esa.int/eogateway/documents/20142/0/Sentinel-1-ESA's-Radar-Observatory-Mission-for-GMES-Operational-Services.pdf | AI9: ESA SP-1322/1 spec table: 'Launch mass 2300 kg (including 130 kg mono-propellant fuel)' | AJ9: n/d - ESA publishes no thruster count | AK9: n/a | AL9: n/a | AM9: n/a | AN9: =IFERROR(AM9+1,"n/a") | AO9: =IFERROR(MAX(0,AK9-AN9),"n/a") | AP9: =IFERROR(MAX(0,FLOOR(AK9/AL9,1)-1),"n/a") | AQ9: =IF(A9="Boosters",IFERROR(MAX(0,MIN(G9-1,FLOOR((R9-T9*g0)/F9,1))),"n/a"),"n/a - not a liftoff vehicle") | AR9: =IF(A9="Boosters",IFERROR(MAX(0,MIN(G9-1,FLOOR((R9-1.2*T9*g0)/F9,1))),"n/a"),"n/a - not a liftoff vehicle") | AS9: n/a | AU9: =IFERROR(MAX(0,AS9-1),"n/a") | AV9: Cannot be estimated: with neither thruster count nor layout published, there is no defensible basis for even a bound. Deliberately left empty rather than guessed.
A10: GEO Satellites | B10: Solar Dynamics Observatory (SDO) | C10: NASA / GSFC | D10: Launch configuration | E10: Aerojet R-4D bipropellant main engine, 110 lbf | F10: 489.3 | G10: 1 | H10: =IFERROR(F10*G10,"n/d") | I10: AMPAC-ISP attitude control thruster, 5 lbf, in four pairs | J10: 22.24 | K10: 8 | L10: =IFERROR(J10*K10,"n/d") | M10: None | N10: 0 | O10: 0 | P10: =IFERROR(N10*O10,"n/d") | Q10: =IFERROR(H10+L10+P10,"incomplete") | R10: =IF(A10="Boosters",SUM(H10,P10),SUM(H10,L10,P10)) | S10: =IF(A10="Boosters",IF(AND(ISNUMBER(H10),ISNUMBER(P10)),"complete","PARTIAL"),IF(ISNUMBER(Q10),"complete","PARTIAL")) | T10: 3100 | U10: 0 | V10: =IFERROR(T10-U10,"n/d") | W10: n/d | X10: 1450 | Y10: =IFERROR(V10*g0,"n/d") | Z10: =IF(AND(S10="PARTIAL",R10=0),"n/d",IFERROR(R10/Y10,"n/d")) | AA10: =IFERROR(X10/V10,"n/d") | AB10: =IFERROR(V10/W10,IFERROR(V10/(V10-X10),"n/d")) | AC10: n/d | AD10: =IFERROR(AC10*g0*LN(AB10),"n/d") | AE10: Direct - primary doc read | AF10: BEST-DOCUMENTED GEO ROW. Flies an INCLINED GEOSYNCHRONOUS orbit, chosen for continuous contact with a single ground station. Unlike operational GEO comsats, NASA published the actual engine ratings in a conference paper: R-4D main engine at 110 lbf and eight ACS thrusters at 5 lbf each. Total 667.2 N, PMF 46.8%. Note the same R-4D engine family appears on Orion (as the 489 N auxiliary engine) - a useful cross-check. | AG10: NASA NTRS 20050243617, 'Attitude Control System Design for the Solar Dynamics Observatory': ACS thruster 'thrust provided by each unit is nominally 5 lbf'; main engine is 'an Aerojet R-4D model bi-propellant engine producing 110 lbf of thrust': https://ntrs.nasa.gov/api/citations/20050243617/downloads/20050243617.pdf | AH10: Same NTRS 20050243617: 'The eight attitude control thrusters are designed and built by AMPAC-ISP, and they are placed in four pairs' | AI10: NASA SDO Press Kit: 'Total mass of the spacecraft at launch is 3,100 kg (8,800 lb); payload 290 kg (640 lb) and fuel 1,450 kg (3,086 lb)': https://sdo.gsfc.nasa.gov/assets/docs/SDO_PressKit.pdf | AJ10: Attitude tier: 8 x 5 lbf ACS thrusters | AK10: 8 | AL10: 4 | AM10: 3 | AN10: =IFERROR(AM10+1,"n/a") | AO10: =IFERROR(MAX(0,AK10-AN10),"n/a") | AP10: =IFERROR(MAX(0,FLOOR(AK10/AL10,1)-1),"n/a") | AQ10: =IF(A10="Boosters",IFERROR(MAX(0,MIN(G10-1,FLOOR((R10-T10*g0)/F10,1))),"n/a"),"n/a - not a liftoff vehicle") | AR10: =IF(A10="Boosters",IFERROR(MAX(0,MIN(G10-1,FLOOR((R10-1.2*T10*g0)/F10,1))),"n/a"),"n/a - not a liftoff vehicle") | AS10: 1 | AT10: 1 x R-4D main engine (110 lbf) | AU10: =IFERROR(MAX(0,AS10-1),"n/a") | AV10: k = 4 is PUBLISHED: NASA states the eight ACS thrusters are 'placed in four pairs' and are 'commanded in pairs to effectuate X-, Y- and Z-axis control torques'. Because commanding is explicitly by PAIR, the loss of one thruster degrades its pair's torque authority immediately, so worst case = 1 is well founded here rather than assumed. Best case = 4. | AW10: Single R-4D performed the GEO orbit-raising burns. Redundancy 0: had it failed, SDO could not have reached its operational orbit.
A11: GEO Satellites | B11: Meteosat Second Generation (MSG) | C11: ESA / EUMETSAT | D11: Launch configuration (GTO) | E11: Liquid Apogee Motor (LAM), 400 N | F11: 400 | G11: 2 | H11: =IFERROR(F11*G11,"n/d") | I11: Reaction Control Thruster (RCT), 10 N | J11: 10 | K11: 6 | L11: =IFERROR(J11*K11,"n/d") | M11: None | N11: 0 | O11: 0 | P11: =IFERROR(N11*O11,"n/d") | Q11: =IFERROR(H11+L11+P11,"incomplete") | R11: =IF(A11="Boosters",SUM(H11,P11),SUM(H11,L11,P11)) | S11: =IF(A11="Boosters",IF(AND(ISNUMBER(H11),ISNUMBER(P11)),"complete","PARTIAL"),IF(ISNUMBER(Q11),"complete","PARTIAL")) | T11: 2000 | U11: 0 | V11: =IFERROR(T11-U11,"n/d") | W11: n/d | X11: 976 | Y11: =IFERROR(V11*g0,"n/d") | Z11: =IF(AND(S11="PARTIAL",R11=0),"n/d",IFERROR(R11/Y11,"n/d")) | AA11: =IFERROR(X11/V11,"n/d") | AB11: =IFERROR(V11/W11,IFERROR(V11/(V11-X11),"n/d")) | AC11: n/d | AD11: =IFERROR(AC11*g0*LN(AB11),"n/d") | AE11: Direct - primary doc read | AF11: The one operational GEO meteorological satellite found with a fully published unified propulsion system: ESA's BR-153 lists 'two 400 N LAMs' and 'six 10 N RCTs' explicitly. Total 860 N, PMF 48.8% - roughly half the launch mass is propellant, which is typical for a GTO-launched GEO satellite that must circularise itself. Spin-stabilised, unusually for a modern GEO platform. | AG11: ESA BR-153, 'Meteosat Second Generation: The Satellite Development': UPS equipment includes 'two 400 N LAMs': https://www.esa.int/esapub/br/br153/br153.pdf | AH11: Same ESA BR-153: 'six 10 N RCTs' | AI11: ESA BR-153: '2000 kg in GTO' launch mass; 'loaded propellant of 976 kg contained in' four tanks | AJ11: Attitude tier: 6 x 10 N RCTs | AK11: 6 | AL11: 3 | AM11: 2 | AN11: =IFERROR(AM11+1,"n/a") | AO11: =IFERROR(MAX(0,AK11-AN11),"n/a") | AP11: =IFERROR(MAX(0,FLOOR(AK11/AL11,1)-1),"n/a") | AQ11: =IF(A11="Boosters",IFERROR(MAX(0,MIN(G11-1,FLOOR((R11-T11*g0)/F11,1))),"n/a"),"n/a - not a liftoff vehicle") | AR11: =IF(A11="Boosters",IFERROR(MAX(0,MIN(G11-1,FLOOR((R11-1.2*T11*g0)/F11,1))),"n/a"),"n/a - not a liftoff vehicle") | AS11: 2 | AT11: 2 x 400 N Liquid Apogee Motors | AU11: =IFERROR(MAX(0,AS11-1),"n/a") | AV11: SPIN-STABILISED, so m = 2 not 3: a spinner needs only spin-axis precession and spin-rate control, with the third axis held gyroscopically. The minimum positive-spanning set is therefore 3, not 4, and best case rises to 3 despite only six thrusters. k = 3 is assumed from the E/W and N/S thruster supports described in ESA BR-153. Spin stabilisation is a genuine redundancy advantage, not just a mass saving. | AW11: Two LAMs for the GTO-to-GEO apogee burns, redundancy 1. With ~49% of launch mass as propellant, losing both would strand the satellite in transfer orbit.
A12: GEO Satellites | B12: GOES-16 (GOES-R) | C12: NOAA / NASA | D12: Launch configuration (fuelled) | E12: Liquid apogee engine (Lockheed Martin A2100A bus) | F12: n/d | G12: n/d | H12: =IFERROR(F12*G12,"n/d") | I12: Chemical RCS thrusters | J12: n/d | K12: n/d | L12: =IFERROR(J12*K12,"n/d") | M12: None | N12: 0 | O12: 0 | P12: =IFERROR(N12*O12,"n/d") | Q12: =IFERROR(H12+L12+P12,"incomplete") | R12: =IF(A12="Boosters",SUM(H12,P12),SUM(H12,L12,P12)) | S12: =IF(A12="Boosters",IF(AND(ISNUMBER(H12),ISNUMBER(P12)),"complete","PARTIAL"),IF(ISNUMBER(Q12),"complete","PARTIAL")) | T12: 5192 | U12: 0 | V12: =IFERROR(T12-U12,"n/d") | W12: 2857 | X12: =IFERROR(V12-W12,"n/d") | Y12: =IFERROR(V12*g0,"n/d") | Z12: =IF(AND(S12="PARTIAL",R12=0),"n/d",IFERROR(R12/Y12,"n/d")) | AA12: =IFERROR(X12/V12,"n/d") | AB12: =IFERROR(V12/W12,IFERROR(V12/(V12-X12),"n/d")) | AC12: n/d | AD12: =IFERROR(AC12*g0*LN(AB12),"n/d") | AE12: Direct - official page read (mass); thrust NOT published | AF12: T/W CANNOT BE CLOSED - and this is the finding, not a gap in the research. NOAA publishes fuelled AND dry mass (so PMF = 45.0% computes exactly) but publishes no propulsion thrust data whatsoever. No substitute was available: operational GEO communications and weather satellite operators essentially never release thruster ratings. Retained to document that. | AG12: NOT PUBLISHED by NOAA/NASA/Lockheed Martin | AH12: NOT PUBLISHED by NOAA/NASA/Lockheed Martin | AI12: NOAA GOES-R Series Spacecraft: fuelled 11,446 lb (5,192 kg), dry 6,299 lb (2,857 kg): https://goes-r.noaa.gov/spacesegment/spacecraft.html | AJ12: n/d - NOAA publishes no thruster count | AK12: n/a | AL12: n/a | AM12: n/a | AN12: =IFERROR(AM12+1,"n/a") | AO12: =IFERROR(MAX(0,AK12-AN12),"n/a") | AP12: =IFERROR(MAX(0,FLOOR(AK12/AL12,1)-1),"n/a") | AQ12: =IF(A12="Boosters",IFERROR(MAX(0,MIN(G12-1,FLOOR((R12-T12*g0)/F12,1))),"n/a"),"n/a - not a liftoff vehicle") | AR12: =IF(A12="Boosters",IFERROR(MAX(0,MIN(G12-1,FLOOR((R12-1.2*T12*g0)/F12,1))),"n/a"),"n/a - not a liftoff vehicle") | AS12: n/a | AU12: =IFERROR(MAX(0,AS12-1),"n/a") | AV12: Cannot be estimated - no thruster count or layout is published for the A2100A bus. Left empty rather than guessed.
A13: GEO Satellites | B13: GOES-19 (GOES-U) | C13: NOAA / NASA | D13: Launch configuration (fuelled) | E13: Liquid apogee engine (Lockheed Martin A2100A bus) | F13: n/d | G13: n/d | H13: =IFERROR(F13*G13,"n/d") | I13: Chemical RCS thrusters | J13: n/d | K13: n/d | L13: =IFERROR(J13*K13,"n/d") | M13: None | N13: 0 | O13: 0 | P13: =IFERROR(N13*O13,"n/d") | Q13: =IFERROR(H13+L13+P13,"incomplete") | R13: =IF(A13="Boosters",SUM(H13,P13),SUM(H13,L13,P13)) | S13: =IF(A13="Boosters",IF(AND(ISNUMBER(H13),ISNUMBER(P13)),"complete","PARTIAL"),IF(ISNUMBER(Q13),"complete","PARTIAL")) | T13: 5000 | U13: 0 | V13: =IFERROR(T13-U13,"n/d") | W13: 2925 | X13: =IFERROR(V13-W13,"n/d") | Y13: =IFERROR(V13*g0,"n/d") | Z13: =IF(AND(S13="PARTIAL",R13=0),"n/d",IFERROR(R13/Y13,"n/d")) | AA13: =IFERROR(X13/V13,"n/d") | AB13: =IFERROR(V13/W13,IFERROR(V13/(V13-X13),"n/d")) | AC13: n/d | AD13: =IFERROR(AC13*g0*LN(AB13),"n/d") | AE13: Direct - official page read (mass); thrust NOT published | AF13: T/W CANNOT BE CLOSED (same reason as GOES-16). Kept because the mass split is instructive: dry mass is HIGHER than GOES-16 while fuelled mass is LOWER, since GOES-U carries the extra CCOR coronagraph and correspondingly less propellant. PMF drops from 45.0% to 41.5% across two satellites of the same bus. | AG13: NOT PUBLISHED by NOAA/NASA/Lockheed Martin | AH13: NOT PUBLISHED by NOAA/NASA/Lockheed Martin | AI13: NOAA GOES-R Series Spacecraft: fuelled 11,023 lb (5,000 kg), dry 6,450 lb (2,925 kg): https://goes-r.noaa.gov/spacesegment/spacecraft.html | AJ13: n/d - NOAA publishes no thruster count | AK13: n/a | AL13: n/a | AM13: n/a | AN13: =IFERROR(AM13+1,"n/a") | AO13: =IFERROR(MAX(0,AK13-AN13),"n/a") | AP13: =IFERROR(MAX(0,FLOOR(AK13/AL13,1)-1),"n/a") | AQ13: =IF(A13="Boosters",IFERROR(MAX(0,MIN(G13-1,FLOOR((R13-T13*g0)/F13,1))),"n/a"),"n/a - not a liftoff vehicle") | AR13: =IF(A13="Boosters",IFERROR(MAX(0,MIN(G13-1,FLOOR((R13-1.2*T13*g0)/F13,1))),"n/a"),"n/a - not a liftoff vehicle") | AS13: n/a | AU13: =IFERROR(MAX(0,AS13-1),"n/a") | AV13: Cannot be estimated - see GOES-16.
A14: Crewed Vehicles | B14: Orion (CM + European Service Module) | C14: NASA / ESA / Airbus | D14: Artemis I, post-insertion | E14: OMS-E (refurbished Shuttle OMS engine, gimballed = TVC) | F14: 26700 | G14: 1 | H14: =IFERROR(F14*G14,"n/d") | I14: 216 N RCS thruster (ArianeGroup, ATV-derived), 6 clusters of 4 | J14: 216 | K14: 24 | L14: =IFERROR(J14*K14,"n/d") | M14: Auxiliary engine (Aerojet Rocketdyne R-4D-11, 164:1 nozzle) | N14: 489 | O14: 8 | P14: =IFERROR(N14*O14,"n/d") | Q14: =IFERROR(H14+L14+P14,"incomplete") | R14: =IF(A14="Boosters",SUM(H14,P14),SUM(H14,L14,P14)) | S14: =IF(A14="Boosters",IF(AND(ISNUMBER(H14),ISNUMBER(P14)),"complete","PARTIAL"),IF(ISNUMBER(Q14),"complete","PARTIAL")) | T14: 26536 | U14: 0 | V14: =IFERROR(T14-U14,"n/d") | X14: 8618 | Y14: =IFERROR(V14*g0,"n/d") | Z14: =IF(AND(S14="PARTIAL",R14=0),"n/d",IFERROR(R14/Y14,"n/d")) | AA14: =IFERROR(X14/V14,"n/d") | AB14: =IFERROR(V14/W14,IFERROR(V14/(V14-X14),"n/d")) | AC14: 310 | AD14: =IFERROR(AC14*g0*LN(AB14),"n/d") | AE14: Direct - primary doc read | AF14: BEST-DOCUMENTED ROW IN THE SHEET - all three propulsion tiers published with counts. Total 26,700 + 24x216 + 8x489 = 35,796 N. Only the OMS-E gimbals (true TVC); Aux pitch/yaw is by off-pulsing a subset of the 8 engines. Isp 310 s is the Aux engine requirement value, so the ideal delta-v shown is indicative for that tier, not a full mission budget. Mass is CM+SM at insertion. | AG14: NASA NTRS 20240003648, Belair, 'Artemis I Orion-ESM Propulsion System Engine Performance', Tab. 2 (OMS-E 26.7 kN), Tab. 3/4 (Aux 489 N x8): https://ntrs.nasa.gov/api/citations/20240003648/downloads/382_BELAIR_ARTEMIS_I_ENGINE_PERFORMANCE_FINAL.pdf | AH14: Same NTRS 20240003648, Tab. 5: 'Thrust 216 N'; twenty-four RCS thrusters in six clusters of four | AI14: NASA 'Orion by the Numbers' (2026): CM+SM insertion mass 58,500 lb (26,536 kg); usable propellant 19,000 lb (8,618 kg): https://www.nasa.gov/wp-content/uploads/2026/01/orion-by-the-numbers-2026b.pdf | AJ14: Attitude tier: 24 x 216 N RCS thrusters | AK14: 24 | AL14: 6 | AM14: 6 | AN14: =IFERROR(AM14+1,"n/a") | AO14: =IFERROR(MAX(0,AK14-AN14),"n/a") | AP14: =IFERROR(MAX(0,FLOOR(AK14/AL14,1)-1),"n/a") | AQ14: =IF(A14="Boosters",IFERROR(MAX(0,MIN(G14-1,FLOOR((R14-T14*g0)/F14,1))),"n/a"),"n/a - not a liftoff vehicle") | AR14: =IF(A14="Boosters",IFERROR(MAX(0,MIN(G14-1,FLOOR((R14-1.2*T14*g0)/F14,1))),"n/a"),"n/a - not a liftoff vehicle") | AS14: 1 | AT14: 1 x OMS-E (the 8 auxiliary engines are their own tier) | AU14: =IFERROR(MAX(0,AS14-1),"n/a") | AV14: STRONGEST CASE IN THE SHEET - both N and k are published, and so is the functional split. NASA states the 24 thrusters form 'six clusters of four', of which 'four provide pitch and yaw' and 'the remaining two clusters provide roll control'. ROLL IS THE BINDING CONSTRAINT: only 2 clusters (8 thrusters) generate roll, split roughly 4 per direction, so losing 4 roll-positive thrusters removes roll authority. Worst case = 3 therefore comes from the published geometry, not from the generic N/k rule - and the two happen to agree (24/6 - 1 = 3), which is a useful validation of the generic rule. | AW14: PROPULSIVE REDUNDANCY 0. Counted as the OMS-E alone. An earlier revision counted 9 (OMS-E + 8 auxiliary engines) and scored 8 - that was the only row in the sheet whose propulsive count spanned two thrust tiers, and it credited the auxiliary engines twice, since they already appear as their own tier. Apollo LM is the direct precedent: it has an aux tier (the APS) and still counts 1. WORTH KNOWING: Orion really does have a backup translational path - NASA describes the 8 R-4D-11s as 'a redundant method for translational thrust' and they flew six burns on Artemis I - so 0 understates the true design margin. The consistent-counting rule is preferred here over crediting it, but the caveat matters.
A15: Crewed Vehicles | B15: Apollo Command & Service Module | C15: NASA / North American Rockwell | D15: Translunar, Block II | E15: SPS (Service Propulsion System, Aerojet AJ10-137, gimballed = TVC) | F15: 91190 | G15: 1 | H15: =IFERROR(F15*G15,"n/d") | I15: SM RCS engine, 100 lbf, 4 quads x 4 engines | J15: 445 | K15: 16 | L15: =IFERROR(J15*K15,"n/d") | M15: None | N15: 0 | O15: 0 | P15: =IFERROR(N15*O15,"n/d") | Q15: =IFERROR(H15+L15+P15,"incomplete") | R15: =IF(A15="Boosters",SUM(H15,P15),SUM(H15,L15,P15)) | S15: =IF(A15="Boosters",IF(AND(ISNUMBER(H15),ISNUMBER(P15)),"complete","PARTIAL"),IF(ISNUMBER(Q15),"complete","PARTIAL")) | T15: 30320 | U15: 0 | V15: =IFERROR(T15-U15,"n/d") | W15: n/d | X15: 18410 | Y15: =IFERROR(V15*g0,"n/d") | Z15: =IF(AND(S15="PARTIAL",R15=0),"n/d",IFERROR(R15/Y15,"n/d")) | AA15: =IFERROR(X15/V15,"n/d") | AB15: =IFERROR(V15/W15,IFERROR(V15/(V15-X15),"n/d")) | AC15: 314 | AD15: =IFERROR(AC15*g0*LN(AB15),"n/d") | AE15: Direct - primary doc read (RCS); AOH value for SPS | AF15: SM RCS only - the 12 Command Module RCS thrusters used after CM/SM separation are EXCLUDED as a separate, independently-fed system. SPS THRUST NEEDS CROSS-CHECKING: the Apollo Operations Handbook gives 20,500 lbf, but NTRS reports quote 20,000 lbf and 21,500 lbf vacuum for different builds. Mass is the late-J-mission CSM; verify against your specific mission. PMF of 60.7% is the highest of any crewed vehicle here. | AG15: NASA Apollo Operations Handbook v1, Sec. 2.4 SPS (20,500 lbf): https://history.nasa.gov/afj/aoh/aoh-v1-2-04-sps.pdf | cross-check NTRS 19730023031 | AH15: NASA NTRS 19730017174, 'Apollo Experience Report - CSM Reaction Control Systems': 'Each of the four engines on each SM quad was a pulse-modulated, radiation-cooled, 100-pound thruster': https://ntrs.nasa.gov/api/citations/19730017174/downloads/19730017174.pdf | AI15: NASA NSSDCA Apollo CSM entries - VERIFY for your specific mission: https://nssdc.gsfc.nasa.gov/nmc/spacecraft/display.action?id=1969-059A | AJ15: Attitude tier: 16 x 445 N SM RCS engines | AK15: 16 | AL15: 4 | AM15: 6 | AN15: =IFERROR(AM15+1,"n/a") | AO15: =IFERROR(MAX(0,AK15-AN15),"n/a") | AP15: =IFERROR(MAX(0,FLOOR(AK15/AL15,1)-1),"n/a") | AQ15: =IF(A15="Boosters",IFERROR(MAX(0,MIN(G15-1,FLOOR((R15-T15*g0)/F15,1))),"n/a"),"n/a - not a liftoff vehicle") | AR15: =IF(A15="Boosters",IFERROR(MAX(0,MIN(G15-1,FLOOR((R15-1.2*T15*g0)/F15,1))),"n/a"),"n/a - not a liftoff vehicle") | AS15: 1 | AT15: 1 x SPS | AU15: =IFERROR(MAX(0,AS15-1),"n/a") | AV15: k = 4 is published (four quads of four). Worst case = 3 corresponds to losing all four thrusters acting in one direction. Historically consistent: Apollo flight rules accepted continuing with quads disabled, and the SM RCS was designed to retain three-axis control with two of four quads - which brackets this estimate from the optimistic side. Best case = 12. | AW15: REDUNDANCY 0 - a true single-point failure. A dead SPS meant no lunar orbit insertion and no trans-Earth injection. This is why Apollo mission rules leaned on the LM descent engine as the backup propulsion path, which is exactly what saved Apollo 13. That backup is a different VEHICLE, so it cannot be counted here.
A16: Crewed Vehicles | B16: Apollo Lunar Module | C16: NASA / Grumman | D16: Apollo 11, at translunar separation | E16: DPS descent engine (throttleable, gimballed = TVC), max thrust | F16: 46700 | G16: 1 | H16: =IFERROR(F16*G16,"n/d") | I16: LM RCS thrust chamber assembly, 100 lbf, 4 quads x 4 | J16: 445 | K16: 16 | L16: =IFERROR(J16*K16,"n/d") | M16: APS ascent engine (fixed, ascent stage only) | N16: 15500 | O16: 1 | P16: =IFERROR(N16*O16,"n/d") | Q16: =IFERROR(H16+L16+P16,"incomplete") | R16: =IF(A16="Boosters",SUM(H16,P16),SUM(H16,L16,P16)) | S16: =IF(A16="Boosters",IF(AND(ISNUMBER(H16),ISNUMBER(P16)),"complete","PARTIAL"),IF(ISNUMBER(Q16),"complete","PARTIAL")) | T16: 15103 | U16: 0 | V16: =IFERROR(T16-U16,"n/d") | W16: 4479 | X16: 10624 | Y16: =IFERROR(V16*g0,"n/d") | Z16: =IF(AND(S16="PARTIAL",R16=0),"n/d",IFERROR(R16/Y16,"n/d")) | AA16: =IFERROR(X16/V16,"n/d") | AB16: =IFERROR(V16/W16,IFERROR(V16/(V16-X16),"n/d")) | AC16: 311 | AD16: =IFERROR(AC16*g0*LN(AB16),"n/d") | AE16: Direct - primary doc read | AF16: DPS AND APS NEVER FIRE TOGETHER - the stages separate, so the 69,320 N total is INSTALLED thrust, not a simultaneous capability. For a landing T/W use the DPS alone against the descent mass. Mass bookkeeping is fully self-consistent: ascent 2,445 dry + 2,376 prop, descent 2,034 dry + 8,248 prop = 15,103 kg, giving the highest PMF of any crewed vehicle in this sheet (70.3%) - the price of landing and taking off again. | AG16: NASA NTRS 20090016298, 'Apollo Lunar Module Propulsion Systems Overview': DPS 'Max Thrust - 46.7 kN (10,500 lbs)'; APS 'Nominal Thrust was 15.5 kN (3500 lbf)': https://ntrs.nasa.gov/api/citations/20090016298/downloads/20090016298.pdf | AH16: Same NTRS 20090016298: '16 thrust chamber assemblies (TCA's)', 'Each produced about 445 N (100 lbf) of thrust' | AI16: NASA NSSDCA, Apollo 11 Lunar Module (1969-059C): total 15,103 kg; ascent stage 2,445 kg dry + 2,376 kg propellant; descent stage 2,034 kg dry + 8,248 kg propellant: https://nssdc.gsfc.nasa.gov/nmc/spacecraft/display.action?id=1969-059C | AJ16: Attitude tier: 16 x 445 N RCS thrust chamber assemblies | AK16: 16 | AL16: 4 | AM16: 6 | AN16: =IFERROR(AM16+1,"n/a") | AO16: =IFERROR(MAX(0,AK16-AN16),"n/a") | AP16: =IFERROR(MAX(0,FLOOR(AK16/AL16,1)-1),"n/a") | AQ16: =IF(A16="Boosters",IFERROR(MAX(0,MIN(G16-1,FLOOR((R16-T16*g0)/F16,1))),"n/a"),"n/a - not a liftoff vehicle") | AR16: =IF(A16="Boosters",IFERROR(MAX(0,MIN(G16-1,FLOOR((R16-1.2*T16*g0)/F16,1))),"n/a"),"n/a - not a liftoff vehicle") | AS16: 1 | AT16: 1 x DPS (descent) / 1 x APS (ascent), single-string each | AU16: =IFERROR(MAX(0,AS16-1),"n/a") | AV16: Same 4-quad geometry as the CSM, so the same bounds apply (best 12, worst 3). IMPORTANT ASYMMETRY: unlike an orbiting spacecraft, the LM had no abort-to-orbit margin during descent, so the OPERATIONALLY acceptable failure count was far below the geometric worst case. Redundancy bounds describe controllability, not mission risk acceptance - a distinction worth making explicitly in a thesis. | AW16: REDUNDANCY 0 IN BOTH PHASES, and the harshest case in the sheet. DPS and APS are not redundant with each other - they serve sequential phases and the descent stage is discarded before ascent. The APS in particular had no backup whatsoever and no abort mode: its failure on the lunar surface was unsurvivable. Grumman mitigated this with extreme simplicity (pressure-fed, ablatively cooled, no throttle) rather than with redundancy.
A17: Crewed Vehicles | B17: Crew Dragon (Dragon 2) | C17: SpaceX | D17: Launch configuration | E17: SuperDraco abort engine, ~15,000 lbf each | F17: 66723 | G17: 8 | H17: =IFERROR(F17*G17,"n/d") | I17: Draco thruster, 90 lbf | J17: 400 | K17: 16 | L17: =IFERROR(J17*K17,"n/d") | M17: None | N17: 0 | O17: 0 | P17: =IFERROR(N17*O17,"n/d") | Q17: =IFERROR(H17+L17+P17,"incomplete") | R17: =IF(A17="Boosters",SUM(H17,P17),SUM(H17,L17,P17)) | S17: =IF(A17="Boosters",IF(AND(ISNUMBER(H17),ISNUMBER(P17)),"complete","PARTIAL"),IF(ISNUMBER(Q17),"complete","PARTIAL")) | T17: n/d | U17: 0 | V17: =IFERROR(T17-U17,"n/d") | W17: n/d | X17: =IFERROR(V17-W17,"n/d") | Y17: =IFERROR(V17*g0,"n/d") | Z17: =IF(AND(S17="PARTIAL",R17=0),"n/d",IFERROR(R17/Y17,"n/d")) | AA17: =IFERROR(X17/V17,"n/d") | AB17: =IFERROR(V17/W17,IFERROR(V17/(V17-X17),"n/d")) | AC17: n/d | AD17: =IFERROR(AC17*g0*LN(AB17),"n/d") | AE17: Official page via search summary (thrust); mass NOT published | AF17: T/W CANNOT BE CLOSED - SpaceX publishes no Crew Dragon gross mass or propellant load in any official document I could reach, and no crewed substitute with fully official data was available beyond the four already in this category. ALSO NOTE: SuperDracos are an ABORT system that never fires in normal flight, so the 533,784 N they contribute is operationally misleading; for on-orbit manoeuvring use the Draco total of 6,400 N alone. | AG17: NASA: 'each instantly producing about 15,000 pounds of thrust', eight SuperDraco engines: https://www.nasa.gov/news-release/spacex-demonstrates-astronaut-escape-system-for-crew-dragon-spacecraft-2/ | AH17: NASA Commercial Crew Program Press Kit: 16 Draco thrusters, each 90 lbf in vacuum: https://www.nasa.gov/commercial-crew-program-press-kit/ | AI17: NOT PUBLISHED by SpaceX | AJ17: Attitude tier: 16 x 90 lbf Draco thrusters | AK17: 16 | AL17: 4 | AM17: 6 | AN17: =IFERROR(AM17+1,"n/a") | AO17: =IFERROR(MAX(0,AK17-AN17),"n/a") | AP17: =IFERROR(MAX(0,FLOOR(AK17/AL17,1)-1),"n/a") | AQ17: =IF(A17="Boosters",IFERROR(MAX(0,MIN(G17-1,FLOOR((R17-T17*g0)/F17,1))),"n/a"),"n/a - not a liftoff vehicle") | AR17: =IF(A17="Boosters",IFERROR(MAX(0,MIN(G17-1,FLOOR((R17-1.2*T17*g0)/F17,1))),"n/a"),"n/a - not a liftoff vehicle") | AS17: n/a | AT17: none separable - the 16 Dracos are already the attitude tier | AU17: =IFERROR(MAX(0,AS17-1),"n/a") | AV17: k = 4 is ASSUMED from the four visible Draco pod locations on the capsule; SpaceX publishes no layout. SuperDracos are deliberately EXCLUDED from this tier - they are abort actuators arranged in four pairs with their own failure logic, and mixing them into an attitude-control redundancy count would be misleading. Bounds are the generic geometric ones and should be treated as indicative. | AW17: NO SEPARATE PROPULSIVE TIER. The 16 Dracos do both attitude control and the deorbit burn, so they are counted once, in the attitude tier. The 8 SuperDracos are abort-only and contribute nothing to nominal mission completion, so there is no separable engine tier at all. OLD (wrong) value was 15. The DRACOS are counted, not the SuperDracos: orbital manoeuvring and the deorbit burn are performed by the 16 Dracos, while the 8 SuperDracos are abort-only and contribute nothing to nominal mission completion. Redundancy 15 by count is optimistic, though - Dracos are arranged in pods and the deorbit burn needs a specific thrust direction, so the effective figure is closer to the attitude-tier worst case.
A18: Deep Space Probes | B18: Juno | C18: NASA / JPL / Lockheed Martin | D18: Launch configuration | E18: Leros-1b bipropellant main engine (FIXED, no gimbal) | F18: 645 | G18: 1 | H18: =IFERROR(F18*G18,"n/d") | I18: Monopropellant hydrazine RCS thruster (4 rocket engine modules) | J18: n/d | K18: 12 | L18: =IFERROR(J18*K18,"n/d") | M18: None | N18: 0 | O18: 0 | P18: =IFERROR(N18*O18,"n/d") | Q18: =IFERROR(H18+L18+P18,"incomplete") | R18: =IF(A18="Boosters",SUM(H18,P18),SUM(H18,L18,P18)) | S18: =IF(A18="Boosters",IF(AND(ISNUMBER(H18),ISNUMBER(P18)),"complete","PARTIAL"),IF(ISNUMBER(Q18),"complete","PARTIAL")) | T18: 3625 | U18: 0 | V18: =IFERROR(T18-U18,"n/d") | W18: 1593 | X18: 2032 | Y18: =IFERROR(V18*g0,"n/d") | Z18: =IF(AND(S18="PARTIAL",R18=0),"n/d",IFERROR(R18/Y18,"n/d")) | AA18: =IFERROR(X18/V18,"n/d") | AB18: =IFERROR(V18/W18,IFERROR(V18/(V18-X18),"n/d")) | AC18: n/d | AD18: =IFERROR(AC18*g0*LN(AB18),"n/d") | AE18: Direct - primary doc read | AF18: The main engine is FIXED, not gimballed - Juno is spin-stabilised, so there is no TVC at all and attitude comes from the 12 RCS thrusters. JPL publishes the RCS count but NOT the per-thruster thrust, so per your rule the T/W is computed from the main engine alone (645 N). Propellant = 1,280 kg fuel + 752 kg oxidiser = 2,032 kg, an exceptionally high PMF of 56.1%. | AG18: NASA JPL Juno Launch Press Kit: 'The Leros-1b main engine is a 645-Newton bi-propellant thruster': https://www.jpl.nasa.gov/news/press_kits/JunoLaunch.pdf | AH18: Same press kit: 'The 12 reaction control system thrusters are mounted on four rocket engine modules' - thrust per thruster NOT published | AI18: Same press kit: 'Weight: 7,992 pounds (3,625 kilograms) total at launch, consisting of 3,513 pounds (1,593 kg) of spacecraft, 2,821 pounds (1,280 kg) of fuel and 1,658 pounds (752 kg) of oxidizer' | AJ18: Attitude tier: 12 monopropellant hydrazine RCS thrusters on 4 rocket engine modules | AK18: 12 | AL18: 4 | AM18: 2 | AN18: =IFERROR(AM18+1,"n/a") | AO18: =IFERROR(MAX(0,AK18-AN18),"n/a") | AP18: =IFERROR(MAX(0,FLOOR(AK18/AL18,1)-1),"n/a") | AQ18: =IF(A18="Boosters",IFERROR(MAX(0,MIN(G18-1,FLOOR((R18-T18*g0)/F18,1))),"n/a"),"n/a - not a liftoff vehicle") | AR18: =IF(A18="Boosters",IFERROR(MAX(0,MIN(G18-1,FLOOR((R18-1.2*T18*g0)/F18,1))),"n/a"),"n/a - not a liftoff vehicle") | AS18: 1 | AT18: 1 x Leros-1b main engine | AU18: =IFERROR(MAX(0,AS18-1),"n/a") | AV18: SPIN-STABILISED, so m = 2 and the minimum set is 3, giving a best case of 9 - unusually high for only 12 thrusters. k = 4 is published ('mounted on four rocket engine modules'), giving worst case 2. Juno also has no TVC at all (fixed main engine), so the RCS is the sole attitude actuator tier and these bounds are the whole story for the spacecraft. | AW18: REDUNDANCY 0. The single Leros-1b performed Jupiter Orbit Insertion; its failure would have meant a flyby instead of an orbital mission. Compounded by the engine being fixed (no gimbal) and by Juno's 56% propellant mass fraction - a large mass of propellant dependent on one engine.
A19: Deep Space Probes | B19: Cassini (Cassini-Huygens) | C19: NASA / JPL / ESA / ASI | D19: Launch configuration | E19: Main Engine A/B, 445 N gimballed (MEB a cold spare, never used) | F19: 445 | G19: 2 | H19: =IFERROR(F19*G19,"n/d") | I19: Monopropellant 1.0 N RCS thruster (2 branches x 8) | J19: 1 | K19: 16 | L19: =IFERROR(J19*K19,"n/d") | M19: None | N19: 0 | O19: 0 | P19: =IFERROR(N19*O19,"n/d") | Q19: =IFERROR(H19+L19+P19,"incomplete") | R19: =IF(A19="Boosters",SUM(H19,P19),SUM(H19,L19,P19)) | S19: =IF(A19="Boosters",IF(AND(ISNUMBER(H19),ISNUMBER(P19)),"complete","PARTIAL"),IF(ISNUMBER(Q19),"complete","PARTIAL")) | T19: 5574 | U19: 0 | V19: =IFERROR(T19-U19,"n/d") | W19: 2523 | X19: =IFERROR(V19-W19,"n/d") | Y19: =IFERROR(V19*g0,"n/d") | Z19: =IF(AND(S19="PARTIAL",R19=0),"n/d",IFERROR(R19/Y19,"n/d")) | AA19: =IFERROR(X19/V19,"n/d") | AB19: =IFERROR(V19/W19,IFERROR(V19/(V19-X19),"n/d")) | AC19: n/d | AD19: =IFERROR(AC19*g0*LN(AB19),"n/d") | AE19: Direct - primary doc read | AF19: REDUNDANCY MATTERS HERE: only ONE of the two 445 N main engines and only ONE of the two 8-thruster RCS branches is ever live. Installed thrust = 906 N; OPERATIONAL thrust = 445 + 8 = 453 N, i.e. half. JPL's own documents are mutually inconsistent on mass (orbiter 5,300 kg + Huygens 350 kg vs. total 5,574 kg / dry 2,523 kg in the same lithograph); the self-consistent 5,574/2,523 pair is used. | AG19: NASA JPL DESCANSO 17: 'two 445 N gimballed thrusters, Main Engine A (MEA) and a redundant Main Engine B (MEB). MEB was never used': https://descanso.jpl.nasa.gov/DPSummary/DESCANSO17_Cassini_RevA.pdf | AH19: Same DESCANSO 17: 'The RCS consisted of two branches of four coupled +/-Y-facing and four uncoupled -Z-facing 1.0 N thrusters' | AI19: NASA JPL Cassini-Huygens lithograph (JPL 400-856A): dry mass 2,523 kg incl. Huygens; total with propellant 5,574 kg: https://solarsystem.nasa.gov/system/downloadable_items/1943_spacecraft.pdf | AJ19: Attitude tier: 16 x 1.0 N monopropellant RCS thrusters (8 per branch) | AK19: 16 | AL19: 4 | AM19: 3 | AN19: =IFERROR(AM19+1,"n/a") | AO19: =IFERROR(MAX(0,AK19-AN19),"n/a") | AP19: =IFERROR(MAX(0,FLOOR(AK19/AL19,1)-1),"n/a") | AQ19: =IF(A19="Boosters",IFERROR(MAX(0,MIN(G19-1,FLOOR((R19-T19*g0)/F19,1))),"n/a"),"n/a - not a liftoff vehicle") | AR19: =IF(A19="Boosters",IFERROR(MAX(0,MIN(G19-1,FLOOR((R19-1.2*T19*g0)/F19,1))),"n/a"),"n/a - not a liftoff vehicle") | AS19: 2 | AT19: 2 x 445 N main engines (MEA + MEB) | AU19: =IFERROR(MAX(0,AS19-1),"n/a") | AV19: Counted at UNIT level across all 16 thrusters per your instruction, k = 4 from the coupled +/-Y and uncoupled -Z groupings. CAVEAT YOU SHOULD KNOW: only one 8-thruster branch is ever live, so the operationally available redundancy is roughly half these numbers (best ~4, worst ~1). The branch structure is precisely the system-level A/B redundancy you excluded - the unit-level figures shown are therefore optimistic relative to how Cassini was actually flown. | AW19: Redundancy 1, and this is genuine one-for-one sparing: MEB was a full cold spare of identical design that was never used across the whole 20-year mission. One of the few true single-unit backups in this sheet.
A20: Deep Space Probes | B20: New Horizons | C20: NASA / JHU-APL | D20: Launch configuration | E20: 4.4 N hydrazine thruster (course correction) | F20: 4.4 | G20: 4 | H20: =IFERROR(F20*G20,"n/d") | I20: 0.8 N hydrazine thruster (pointing, spin up/down) | J20: 0.8 | K20: 12 | L20: =IFERROR(J20*K20,"n/d") | M20: None | N20: 0 | O20: 0 | P20: =IFERROR(N20*O20,"n/d") | Q20: =IFERROR(H20+L20+P20,"incomplete") | R20: =IF(A20="Boosters",SUM(H20,P20),SUM(H20,L20,P20)) | S20: =IF(A20="Boosters",IF(AND(ISNUMBER(H20),ISNUMBER(P20)),"complete","PARTIAL"),IF(ISNUMBER(Q20),"complete","PARTIAL")) | T20: 478 | U20: 0 | V20: =IFERROR(T20-U20,"n/d") | X20: 77 | Y20: =IFERROR(V20*g0,"n/d") | Z20: =IF(AND(S20="PARTIAL",R20=0),"n/d",IFERROR(R20/Y20,"n/d")) | AA20: =IFERROR(X20/V20,"n/d") | AB20: =IFERROR(V20/W20,IFERROR(V20/(V20-X20),"n/d")) | AC20: n/d | AD20: =IFERROR(AC20*g0*LN(AB20),"n/d") | AE20: Official page via search summary - re-verify | AF20: No true main engine - the four 4.4 N thrusters serve that role, so the 'main' tier here is really a larger class of the same monopropellant thruster. 16 thrusters in 8 locations, 27.2 N total. Lowest PMF of the deep-space set (16.1%) because New Horizons was a pure flyby: it needed no orbit-insertion burn, which is exactly why it could be launched so fast. | AG20: NASA/JHU-APL New Horizons spacecraft page: 'Four of these thrusters, each of which provides 4.4 Newtons (1 pound) of force are used for course corrections': https://newhorizons.jhuapl.edu/Mission/Spacecraft.php | AH20: Same page: 'twelve smaller thrusters - each providing 0.8 Newtons of thrust - to point, spin up and spin down the spacecraft' | AI20: NASA New Horizons Launch Press Kit: 'Launch weight: 478 kilograms (1,054 pounds); includes 77 kilograms (170 pounds) of hydrazine propellant': https://www.nasa.gov/wp-content/uploads/2015/03/139889main_presskit12_05.pdf | AJ20: Attitude tier: 12 x 0.8 N hydrazine monopropellant thrusters (the 4 x 4.4 N units are the propulsive tier) | AK20: 12 | AL20: 8 | AM20: 3 | AN20: =IFERROR(AM20+1,"n/a") | AO20: =IFERROR(MAX(0,AK20-AN20),"n/a") | AP20: =IFERROR(MAX(0,FLOOR(AK20/AL20,1)-1),"n/a") | AQ20: =IF(A20="Boosters",IFERROR(MAX(0,MIN(G20-1,FLOOR((R20-T20*g0)/F20,1))),"n/a"),"n/a - not a liftoff vehicle") | AR20: =IF(A20="Boosters",IFERROR(MAX(0,MIN(G20-1,FLOOR((R20-1.2*T20*g0)/F20,1))),"n/a"),"n/a - not a liftoff vehicle") | AS20: 4 | AT20: 4 x 4.4 N hydrazine course-correction thrusters | AU20: =IFERROR(MAX(0,AS20-1),"n/a") | AV20: k = 8 is published ('mounted across the spacecraft in eight locations'). The fine dispersal gives a low worst case (1) because each location carries only two thrusters, but the mixed thrust classes complicate this: the four 4.4 N units are not interchangeable with the twelve 0.8 N units, so a loss among the larger class degrades trajectory-correction authority specifically. The single-figure bound understates that nuance. | AW20: Redundancy 3. No dedicated main engine - the four larger thrusters perform trajectory correction, and with four of them the propulsive tier is comparatively robust. This mattered: precise TCMs were what delivered the Pluto and Arrokoth encounters.
A21: Deep Space Probes | B21: Europa Clipper | C21: NASA / JPL / APL | D21: Launch configuration | E21: 27.5 N engine (24 installed; max 8 fired simultaneously) | F21: 27.5 | G21: 24 | H21: =IFERROR(F21*G21,"n/d") | I21: Same engine set - no separate RCS tier | J21: 0 | K21: 0 | L21: =IFERROR(J21*K21,"n/d") | M21: None | N21: 0 | O21: 0 | P21: =IFERROR(N21*O21,"n/d") | Q21: =IFERROR(H21+L21+P21,"incomplete") | R21: =IF(A21="Boosters",SUM(H21,P21),SUM(H21,L21,P21)) | S21: =IF(A21="Boosters",IF(AND(ISNUMBER(H21),ISNUMBER(P21)),"complete","PARTIAL"),IF(ISNUMBER(Q21),"complete","PARTIAL")) | T21: 5800 | U21: 0 | V21: =IFERROR(T21-U21,"n/d") | X21: 2750 | Y21: =IFERROR(V21*g0,"n/d") | Z21: =IF(AND(S21="PARTIAL",R21=0),"n/d",IFERROR(R21/Y21,"n/d")) | AA21: =IFERROR(X21/V21,"n/d") | AB21: =IFERROR(V21/W21,IFERROR(V21/(V21-X21),"n/d")) | AC21: n/d | AD21: =IFERROR(AC21*g0*LN(AB21),"n/d") | AE21: Official page via search summary - re-verify | AF21: ARCHITECTURALLY DIFFERENT: no main-engine/RCS split at all - one homogeneous set of 24 x 27.5 N engines does both jobs. Installed thrust 660 N, but NASA states a MAXIMUM SIMULTANEOUS thrust of 220 N (8 engines at once), so the real manoeuvring T/W is one third of the value computed here. PMF 47.4%. | AG21: NASA JPL Europa Clipper press kit: 'The system's 24 engines, each capable of generating 27.5 newtons of thrust, are used up to eight at a time for a maximum thrust of 220 newtons': https://www.jpl.nasa.gov/press-kits/europa-clipper/mission/spacecraft/ | AH21: n/a - the same 24 engines provide attitude control | AI21: Same press kit: '~12,800 pounds (about 5,800 kilograms), including about 6,060 pounds (about 2,750 kilograms) of propellant' | AJ21: Propulsion tier: 24 x 27.5 N engines (attitude + translation) | AK21: 24 | AL21: 6 | AM21: 3 | AN21: =IFERROR(AM21+1,"n/a") | AO21: =IFERROR(MAX(0,AK21-AN21),"n/a") | AP21: =IFERROR(MAX(0,FLOOR(AK21/AL21,1)-1),"n/a") | AQ21: =IF(A21="Boosters",IFERROR(MAX(0,MIN(G21-1,FLOOR((R21-T21*g0)/F21,1))),"n/a"),"n/a - not a liftoff vehicle") | AR21: =IF(A21="Boosters",IFERROR(MAX(0,MIN(G21-1,FLOOR((R21-1.2*T21*g0)/F21,1))),"n/a"),"n/a - not a liftoff vehicle") | AS21: n/a | AT21: none separable - the 24 engines are already the attitude tier | AU21: =IFERROR(MAX(0,AS21-1),"n/a") | AV21: HOMOGENEOUS ARCHITECTURE is a redundancy advantage: with no main/RCS split, all 24 identical engines are mutually substitutable, so the best case of 20 is more physically plausible here than for a mixed-thruster spacecraft. k = 6 is assumed. Additional slack comes from the operating rule that only 8 of 24 fire at once - the system is thrust-limited, not actuator-limited, so failures degrade redundancy long before performance. | AW21: NO SEPARATE PROPULSIVE TIER. Europa Clipper has no main engine: the same 24 x 27.5 N engines that hold attitude also perform every translational burn. Counting them here as well as in the attitude tier would credit one set of hardware twice, which is what an earlier revision of this sheet did. They are counted once, in the attitude tier, and the propulsive term contributes nothing. OLD (wrong) value was 23. Redundancy 23 by count - nominally the highest in the sheet, because the architecture is homogeneous and every engine is substitutable. Temper it with the operating rule that only 8 fire at once: the system is thrust-limited, so enough failures eventually stop it reaching the 220 N needed for large burns even while control authority survives.
A22: Deep Space Probes | B22: Voyager 1 | C22: NASA / JPL | D22: Launch configuration (1977) | E22: None - no main engine (propulsion module jettisoned after launch) | F22: 0 | G22: 0 | H22: =IFERROR(F22*G22,"n/d") | I22: Hydrazine thruster (12 attitude control + 4 TCM) | J22: 0.85 | K22: 16 | L22: =IFERROR(J22*K22,"n/d") | M22: None | N22: 0 | O22: 0 | P22: =IFERROR(N22*O22,"n/d") | Q22: =IFERROR(H22+L22+P22,"incomplete") | R22: =IF(A22="Boosters",SUM(H22,P22),SUM(H22,L22,P22)) | S22: =IF(A22="Boosters",IF(AND(ISNUMBER(H22),ISNUMBER(P22)),"complete","PARTIAL"),IF(ISNUMBER(Q22),"complete","PARTIAL")) | T22: 815 | U22: 0 | V22: =IFERROR(T22-U22,"n/d") | W22: n/d | X22: =IFERROR(V22-W22,"n/d") | Y22: =IFERROR(V22*g0,"n/d") | Z22: =IF(AND(S22="PARTIAL",R22=0),"n/d",IFERROR(R22/Y22,"n/d")) | AA22: =IFERROR(X22/V22,"n/d") | AB22: =IFERROR(V22/W22,IFERROR(V22/(V22-X22),"n/d")) | AC22: n/d | AD22: =IFERROR(AC22*g0*LN(AB22),"n/d") | AE22: Official page via search summary - re-verify | AF22: All propulsion is the RCS tier, so per your rule T/W is computed from the 16 thrusters alone. JPL describes thrust only qualitatively as 'three ounces' (~0.85 N); the 0.89 N figure quoted widely elsewhere is NOT in any official JPL source, so 0.85 N is used. Launch mass 815 kg is stated 'including hydrazine' but the hydrazine load is not broken out, so PMF cannot be computed. | AG22: n/a - no main engine | AH22: NASA JPL Voyager FAQ: 12 attitude-control and 4 trajectory-correction hydrazine thrusters; 'each of the Voyager thrusters has a thrust of only three ounces': https://science.nasa.gov/mission/voyager/frequently-asked-questions/ | AI22: NASA JPL Voyager fact sheet: launch mass including hydrazine 815 kg: https://science.nasa.gov/mission/voyager/fact-sheet/ | AJ22: Attitude tier: 12 hydrazine monopropellant attitude-control thrusters (the 4 TCM units are the propulsive tier) | AK22: 12 | AL22: 4 | AM22: 3 | AN22: =IFERROR(AM22+1,"n/a") | AO22: =IFERROR(MAX(0,AK22-AN22),"n/a") | AP22: =IFERROR(MAX(0,FLOOR(AK22/AL22,1)-1),"n/a") | AQ22: =IF(A22="Boosters",IFERROR(MAX(0,MIN(G22-1,FLOOR((R22-T22*g0)/F22,1))),"n/a"),"n/a - not a liftoff vehicle") | AR22: =IF(A22="Boosters",IFERROR(MAX(0,MIN(G22-1,FLOOR((R22-1.2*T22*g0)/F22,1))),"n/a"),"n/a - not a liftoff vehicle") | AS22: 4 | AT22: 4 x hydrazine trajectory-correction-manoeuvre thrusters | AU22: =IFERROR(MAX(0,AS22-1),"n/a") | AV22: k = 4 assumed. Real flight history brackets these bounds usefully: Voyager 1 has outlived multiple thruster failures and clogging events over 48 years and has been commanded to swap between thruster sets, demonstrating that the true tolerated failure count sits well above the worst case of 3 - though those swaps were between redundant sets, i.e. system-level. | AW22: Redundancy 3. The 12 attitude-control thrusters are excluded from the propulsive count as they are fine-pointing actuators. Voyager 1 has in fact outlived several thruster failures and been commanded onto backup sets over 48 years.
